Workbook

Sheet assoi
A3: Счет АССОИ | B3: Счет КИС | C3: Код продукции(статьи) АССОИ | D3: Имя продукции(статьи) АССОИ | E3: Продукция КИС | F3: Код контрагента АССОИ | G3: Контрагент АССОИ | H3: Код Контрагента КИС | I3: Контрагент КИС | J3: Валюта | K3: Ед.Изм | L3: Период | M3: Год | N3: Колонка | O3: Значение (2 373 601) | P3: По модулю | Q3: coef | R3: Комментарий
A6: BA090_08 | B6: 90.1010000 | C6: m15031600 | D6: Катоды медные | E6: 89688 | F6: 2280 | G6: ПАО "КУЗОЦМ" | H6: 1258 | I6: КУЗОЦМ АО | J6: RUB*1000 | K6: NONE | L6: 111 | M6: 2022 | N6: SLSSFIX | O6: 70067 | P6: false | R6: 70066585,68999999800000 RUB*1000 > RUB*1000;
A7: BA090_08 | B7: 90.1010000 | C7: m15032100 | D7: Слитки медные | E7: 651433 | F7: 12375 | G7: СТМ ООО | H7: 208535 | I7: СТМ ООО | J7: RUB*1000 | K7: NONE | L7: 111 | M7: 2022 | N7: SLSSFIX | O7: 3096 | P7: false | R7: 3096018,79999999980000 RUB*1000 > RUB*1000;
A8: BA090_08 | B8: 90.1010000 | C8: m15032100 | D8: Слитки медные | E8: 695002 | F8: 9950 | G8: ООО "ЛИСТ СПб" | H8: 69920 | I8: ЛИСТ СПБ ООО | J8: RUB*1000 | K8: NONE | L8: 111 | M8: 2022 | N8: SLSSFIX | O8: 543 | P8: false | R8: 542974,15000000002000 RUB*1000 > RUB*1000;
A9: BA090_08 | B9: 90.1010000 | C9: m15041130 | D9: Прокат медный | E9: 650280, 650281, 650282, 650622, 650623, 663965 | F9: 10722 | G9: ООО "НПЦ Металлург" | H9: 66325 | I9: НПЦ МЕТАЛЛУРГ ООО | J9: RUB*1000 | K9: NONE | L9: 111 | M9: 2022 | N9: SLSSFIX | O9: 11807 | P9: false | R9: 6168588,79999999980000 + 616319,76000000001000 + 1265600,00000000000000 + 1231494,39999999990000 + 1232729,60000000010000 + 1292177,60000000010000 RUB*1000 > RUB*1000;
A10: BA090_08 | B10: 90.1010000 | C10: m15041130 | D10: Прокат медный | E10: 651017, 651214, 651221, 652055, 652143, 652158, 652159, 652164, 652167, 652335, 652347, 652350, 652356, 652369, 653190, 653191, 653195, 653230, 653343, 653350, 658575, 670179 | F10: 10723 | G10: ООО "АЛЬМЕТ" | H10: 126128 | I10: АЛЬМЕТ ООО | J10: RUB*1000 | K10: NONE | L10: 111 | M10: 2022 | N10: SLSSFIX | O10: 5299 | P10: false | R10: 191394,00000000000000 + 242625,60000000001000 + 295214,40000000002000 + 232835,20000000001000 + 194544,00000000000000 + 413613,59999999998000 + 303959,26000000001000 + 184710,39999999999000 + 177868,79999999999000 + 192128,39999999999000 + 218661,84000000000000 + 167865,84000000000000 + 277286,40000000002000 + 114918,48000000000000 + 181670,39999999999000 + 179280,00000000000000 + 180475,20000000001000 + 364834,79999999999000 + 422783,46000000002000 + 177366,29999999999000 + 392836,00000000000000 + 192073,60000000001000 RUB*1000 > RUB*1000;
A11: BA090_08 | B11: 90.1010000 | C11: m15041130 | D11: Прокат медный | E11: 659579, 659580, 659582, 659583, 660033, 660039, 660043, 660067 | F11: 10837 | G11: ООО "СВЕРДЛОВЭЛЕКТРО" | H11: 20784 | I11: СВЕРДЛОВЭЛЕКТРО ООО | J11: RUB*1000 | K11: NONE | L11: 111 | M11: 2022 | N11: SLSSFIX | O11: 10133 | P11: false | R11: 2282269,99000000020000 + 1088811,93999999990000 + 1384662,36000000010000 + 2291278,24000000020000 + 1104642,00000000000000 + 396272,34999999998000 + 520008,00000000000000 + 1065463,20000000000000 RUB*1000 > RUB*1000;
A12: BA090_08 | B12: 90.1010000 | C12: m15041130 | D12: Прокат медный | E12: 651299, 653277 | F12: 10842 | G12: ООО "СПИРАЛЬ" | H12: 124818 | I12: СПИРАЛЬ ООО | J12: RUB*1000 | K12: NONE | L12: 111 | M12: 2022 | N12: SLSSFIX | O12: 5982 | P12: false | R12: 1228702,80000000000000 + 4752990,91999999990000 RUB*1000 > RUB*1000;
A13: BA090_08 | B13: 90.1010000 | C13: m15041130 | D13: Прокат медный | E13: 651495 | F13: 10845 | G13: ООО "Уромгаз-Ирбит" | H13: 125683 | I13: УРОМГАЗ-ИРБИТ ООО | J13: RUB*1000 | K13: NONE | L13: 111 | M13: 2022 | N13: SLSSFIX | O13: 1453 | P13: false | R13: 1452897,60000000010000 RUB*1000 > RUB*1000;
A14: BA090_08 | B14: 90.1010000 | C14: m15041130 | D14: Прокат медный | E14: 653795 | F14: 10848 | G14: АО "ПОЗИС" | H14: 135819 | I14: ПОЗИС АО | J14: RUB*1000 | K14: NONE | L14: 111 | M14: 2022 | N14: SLSSFIX | O14: 1257 | P14: false | R14: 1257186,08000000010000 RUB*1000 > RUB*1000;
A15: BA090_08 | B15: 90.1010000 | C15: m15041130 | D15: Прокат медный | E15: 650648, 650649, 650652, 650654, 650655 | F15: 10856 | G15: АО "ДКС" | H15: 205357 | I15: ДКС АО | J15: RUB*1000 | K15: NONE | L15: 111 | M15: 2022 | N15: SLSSFIX | O15: 6918 | P15: false | R15: 213344,00000000000000 + 348582,40000000002000 + 1524736,39999999990000 + 1802214,39999999990000 + 3029484,79999999980000 RUB*1000 > RUB*1000;
A16: BA090_08 | B16: 90.1010000 | C16: m15041130 | D16: Прокат медный | E16: 651618, 652821, 652830, 652840, 652841, 652862, 655511, 655528, 655543, 656741, 656798, 656824, 656826, 656834, 656841, 657899, 657919, 658568, 658570, 658574, 658577, 659542, 659544, 659995, 660328, 660332 | F16: 10857 | G16: НПК МЕТАПРОМ ООО | H16: 208503 | I16: НПК МЕТАПРОМ ООО | J16: RUB*1000 | K16: NONE | L16: 111 | M16: 2022 | N16: SLSSFIX | O16: 22795 | P16: false | R16: 281799,29999999999000 + 941978,43999999994000 + 1155304,76000000000000 + 762233,43999999994000 + 592992,00000000000000 + 574248,00000000000000 + 114736,00000000000000 + 1016720,00000000000000 + 1545528,00000000000000 + 225876,60000000001000 + 135710,39999999999000 + 461959,67999999999000 + 809172,19999999995000 + 1421405,96000000000000 + 789493,12000000000000 + 1077014,36000000010000 + 3405461,39999999990000 + 1872873,20000000000000 + 179864,35999999999000 + 501006,67999999999000 + 937418,35999999999000 + 492219,29999999999000 + 1333501,70000000000000 + 1698140,08000000010000 + 342057,59999999998000 + 126454,16000000000000 RUB*1000 > RUB*1000;
A17: BA090_08 | B17: 90.1010000 | C17: m15041130 | D17: Прокат медный | E17: 652454, 652459, 653909, 654056, 707800 | F17: 10858 | G17: МЕЛЬХИОР ООО | H17: 208504 | I17: МЕЛЬХИОР ООО | J17: RUB*1000 | K17: NONE | L17: 111 | M17: 2022 | N17: SLSSFIX | O17: 17010 | P17: false | R17: 294814,96000000002000 + 765592,12000000000000 + 359668,40000000002000 + 2029020,00000000000000 + 13561246,80000000100000 RUB*1000 > RUB*1000;
A18: BA090_08 | B18: 90.1010000 | C18: m15041130 | D18: Прокат медный | E18: 650623, 652596 | F18: 10860 | G18: АО "СКБ СИБЭЛЕКТРОТЕРМ" | H18: 208553 | I18: СКБ СИБЭЛЕКТРОТЕРМ АО | J18: RUB*1000 | K18: NONE | L18: 111 | M18: 2022 | N18: SLSSFIX | O18: 3409 | P18: false | R18: 2640808,79999999980000 + 768592,80000000005000 RUB*1000 > RUB*1000;
A19: BA090_08 | B19: 90.1010000 | C19: m15041130 | D19: Прокат медный | E19: 650953, 681414 | F19: 10862 | G19: АО "АМЕТИСТ-СТАН" | H19: 208597 | I19: АМЕТИСТ-СТАН АО | J19: RUB*1000 | K19: NONE | L19: 111 | M19: 2022 | N19: SLSSFIX | O19: 4192 | P19: false | R19: 174768,00000000000000 + 4016942,18000000020000 RUB*1000 > RUB*1000;
A20: BA090_08 | B20: 90.1010000 | C20: m15041130 | D20: Прокат медный | E20: 653277 | F20: 10863 | G20: ООО "СПИРАЛЬПЛЮС" | H20: 208609 | I20: СПИРАЛЬПЛЮС ООО | J20: RUB*1000 | K20: NONE | L20: 111 | M20: 2022 | N20: SLSSFIX | O20: 2401 | P20: false | R20: 2401331,39999999990000 RUB*1000 > RUB*1000;
A21: BA090_08 | B21: 90.1010000 | C21: m15041130 | D21: Прокат медный | E21: 658887, 659366, 659781, 660276, 698976 | F21: 10866 | G21: ООО "ТДР" | H21: 208686 | I21: ТДР ООО | J21: RUB*1000 | K21: NONE | L21: 111 | M21: 2022 | N21: SLSSFIX | O21: 7617 | P21: false | R21: 4389469,00000000000000 + 1102155,20000000000000 + 300868,59999999998000 + 1257840,80000000000000 + 566522,59999999998000 RUB*1000 > RUB*1000;
A22: BA090_08 | B22: 90.1010000 | C22: m15041130 | D22: Прокат медный | E22: 651540 | F22: 10875 | G22: АО "ТЭМЗ" | H22: 5028 | I22: ТЭМЗ АО | J22: RUB*1000 | K22: NONE | L22: 111 | M22: 2022 | N22: SLSSFIX | O22: 104 | P22: false | R22: 103542,39999999999000 RUB*1000 > RUB*1000;
A23: BA090_08 | B23: 90.1010000 | C23: m15041130 | D23: Прокат медный | E23: 657944 | F23: 12340 | G23: ООО "Сплав М" | H23: 72909 | I23: СПЛАВ М ООО | J23: RUB*1000 | K23: NONE | L23: 111 | M23: 2022 | N23: SLSSFIX | O23: 2036 | P23: false | R23: 2035516,80000000000000 RUB*1000 > RUB*1000;
A24: BA090_08 | B24: 90.1010000 | C24: m15041130 | D24: Прокат медный | E24: 650280 | F24: 12344 | G24: ООО "Маркетинг-Бюро. Металл" | H24: 123157 | I24: МАРКЕТИНГ-БЮРО.МЕТАЛЛ ООО | J24: RUB*1000 | K24: NONE | L24: 111 | M24: 2022 | N24: SLSSFIX | O24: 190 | P24: false | R24: 190296,12000000000000 RUB*1000 > RUB*1000;
A25: BA090_08 | B25: 90.1010000 | C25: m15041130 | D25: Прокат медный | E25: 654011, 655463, 655467 | F25: 12348 | G25: ООО "КамаМеталлКомплект" | H25: 124717 | I25: КАМАМЕТАЛЛКОМПЛЕКТ ООО | J25: RUB*1000 | K25: NONE | L25: 111 | M25: 2022 | N25: SLSSFIX | O25: 1982 | P25: false | R25: 1004631,60000000000000 + 753654,00000000000000 + 223572,00000000000000 RUB*1000 > RUB*1000;
A26: BA090_08 | B26: 90.1010000 | C26: m15041130 | D26: Прокат медный | E26: 701200 | F26: 12349 | G26: ООО "СИМЕНС ЭНЕРГЕТИКА ТРАНСФОРМАТОРЫ" | H26: 125023 | I26: ВОРОНЕЖСКИЙ ТРАНСФОРМАТОР ООО | J26: RUB*1000 | K26: NONE | L26: 111 | M26: 2022 | N26: SLSSFIX | O26: 415 | P26: false | R26: 414752,40000000002000 RUB*1000 > RUB*1000;
A27: BA090_08 | B27: 90.1010000 | C27: m15041130 | D27: Прокат медный | E27: 650390, 709580, 709581 | F27: 12351 | G27: ООО "СМЦ Маркетинг-Бюро" | H27: 125117 | I27: СМЦ МАРКЕТИНГ-БЮРО ООО | J27: RUB*1000 | K27: NONE | L27: 111 | M27: 2022 | N27: SLSSFIX | O27: 673 | P27: false | R27: 298845,79999999999000 + 182603,51999999999000 + 191480,07999999999000 RUB*1000 > RUB*1000;
A28: BA090_08 | B28: 90.1010000 | C28: m15041130 | D28: Прокат медный | E28: 658931 | F28: 12352 | G28: ООО "ПЛАСТИКПАК" | H28: 125440 | I28: ПЛАСТИКПАК ООО | J28: RUB*1000 | K28: NONE | L28: 111 | M28: 2022 | N28: SLSSFIX | O28: 172 | P28: false | R28: 172221,60000000001000 RUB*1000 > RUB*1000;
A29: BA090_08 | B29: 90.1010000 | C29: m15041130 | D29: Прокат медный | E29: 652742 | F29: 12353 | G29: ООО "Кабельная арматура" | H29: 125835 | I29: КАБЕЛЬНАЯ АРМАТУРА ООО | J29: RUB*1000 | K29: NONE | L29: 111 | M29: 2022 | N29: SLSSFIX | O29: 311 | P29: false | R29: 311304,00000000000000 RUB*1000 > RUB*1000;
A30: BA090_08 | B30: 90.1010000 | C30: m15041130 | D30: Прокат медный | E30: 651781, 653994, 654046, 654049, 656712, 656714, 686969, 688157, 689570, 690141, 690142, 691750, 691753, 693046, 693047, 693197, 693198, 694646, 694647, 695198, 696928, 700560, 705218 | F30: 12354 | G30: ООО "ДПА" | H30: 125847 | I30: ДПА ООО | J30: RUB*1000 | K30: NONE | L30: 111 | M30: 2022 | N30: SLSSFIX | O30: 10550 | P30: false | R30: 657262,90000000002000 + 832611,15000000002000 + 152237,79999999999000 + 621336,09999999998000 + 368763,59999999998000 + 185731,00000000000000 + 392801,79999999999000 + 670945,56000000006000 + 532117,80000000005000 + 314976,40000000002000 + 703617,59999999998000 + 983129,17000000004000 + 295221,59999999998000 + 777096,69999999995000 + 431033,64000000001000 + 337632,75000000000000 + 378693,00000000000000 + 308096,03999999998000 + 190329,60000000001000 + 275780,70000000001000 + 362589,50000000000000 + 301553,46000000002000 + 476168,09999999998000 RUB*1000 > RUB*1000;
A31: BA090_08 | B31: 90.1010000 | C31: m15041130 | D31: Прокат медный | E31: 653414 | F31: 12364 | G31: ООО "МИКОМЕТ" | H31: 193632 | I31: МИКОМЕТ ООО | J31: RUB*1000 | K31: NONE | L31: 111 | M31: 2022 | N31: SLSSFIX | O31: 1294 | P31: false | R31: 1293619,50000000000000 RUB*1000 > RUB*1000;
A32: BA090_08 | B32: 90.1010000 | C32: m15041130 | D32: Прокат медный | E32: 650168, 651250 | F32: 12369 | G32: ООО "МПК ИННОМЕТ" | H32: 195025 | I32: МПК ИННОМЕТ ООО | J32: RUB*1000 | K32: NONE | L32: 111 | M32: 2022 | N32: SLSSFIX | O32: 3232 | P32: false | R32: 2727743,60000000010000 + 504665,70000000001000 RUB*1000 > RUB*1000;
A33: BA090_08 | B33: 90.1010000 | C33: m15041130 | D33: Прокат медный | E33: 651278, 653230 | F33: 12370 | G33: АО "ЭЛЕКТРУМ АВ" | H33: 195052 | I33: ЭЛЕКТРУМ АВ АО | J33: RUB*1000 | K33: NONE | L33: 111 | M33: 2022 | N33: SLSSFIX | O33: 504 | P33: false | R33: 236232,00000000000000 + 267729,59999999998000 RUB*1000 > RUB*1000;
A34: BA090_08 | B34: 90.1010000 | C34: m15041130 | D34: Прокат медный | E34: 651640, 652748, 654758, 654976, 656341, 656345, 656350, 656366, 656372, 656393, 656396, 657860, 658322, 658882, 658919, 658938, 659373, 659374, 659376, 659419, 659774, 659778, 659782, 659788, 659790, 673546, 673554 | F34: 12371 | G34: ООО "ВЕНДОР-Проф" | H34: 195097 | I34: ВЕНДОР-ПРОФ ООО | J34: RUB*1000 | K34: NONE | L34: 111 | M34: 2022 | N34: SLSSFIX | O34: 6824 | P34: false | R34: 744604,00000000000000 + 341628,00000000000000 + 718536,96999999997000 + 219016,69000000000000 + 211297,17000000001000 + 1704,55999999999990 + 588026,90000000002000 + 46749,26000000000200 + 159617,20999999999000 + 158318,39000000001000 + 230609,60999999999000 + 712910,06000000006000 + 7892,96000000000000 + 715598,93000000005000 + 33701,19000000000200 + 252000,00000000000000 + 1097512,00000000000000 + 8442,39999999999960 + 135302,20000000001000 + 102900,72000000000000 + 57583,88999999999900 + 9461,70000000000070 + 15679,50000000000000 + 29764,86999999999900 + 12287,25000000000000 + 86039,89999999999400 + 126624,89999999999000 RUB*1000 > RUB*1000;
A35: BA090_08 | B35: 90.1010000 | C35: m15041130 | D35: Прокат медный | E35: 650289, 651214, 653216 | F35: 12386 | G35: ТОРГОВО-ПРОИЗВОДСТВЕННОЕ УНИТАРНОЕ ПРЕДПРИЯТИЕ "КОЛОРПРОКАТ" | H35: 208941 | I35: КОЛОРПРОКАТ ТП УП | J35: RUB*1000 | K35: NONE | L35: 111 | M35: 2022 | N35: SLSSFIX | O35: 649 | P35: false | R35: 190382,39999999999000 + 288100,00000000000000 + 170555,20000000001000 RUB*1000 > RUB*1000;
A36: BA090_08 | B36: 90.1010000 | C36: m15041130 | D36: Прокат медный | E36: 651331, 651336, 651341, 651345, 653301, 691093 | F36: 12387 | G36: ОАО "МИНСКИЙ ЭЛЕКТРОТЕХНИЧЕСКИЙ ЗАВОД ИМЕНИ В.И. КОЗЛОВА" | H36: 208986 | I36: МЭТЗ ИМ. В.И.КОЗЛОВА ОАО | J36: RUB*1000 | K36: NONE | L36: 111 | M36: 2022 | N36: SLSSFIX | O36: 7227 | P36: false | R36: 179139,20000000001000 + 615851,52000000002000 + 3651655,75999999980000 + 1883685,00000000000000 + 594306,40000000002000 + 302600,00000000000000 RUB*1000 > RUB*1000;
A37: BA090_08 | B37: 90.1010000 | C37: m15041130 | D37: Прокат медный | E37: 650990 | F37: 12396 | G37: ООО "ФОНД-МЕТАЛЛ" | H37: 115136 | I37: ФОНД-МЕТАЛЛ ООО | J37: RUB*1000 | K37: NONE | L37: 111 | M37: 2022 | N37: SLSSFIX | O37: 649 | P37: false | R37: 648924,00000000000000 RUB*1000 > RUB*1000;
A38: BA090_08 | B38: 90.1010000 | C38: m15041130 | D38: Прокат медный | E38: 695691 | F38: 12398 | G38: ООО ТК "АКТИМИСТА" | H38: 122083 | I38: ТК АКТИМИСТА ООО | J38: RUB*1000 | K38: NONE | L38: 111 | M38: 2022 | N38: SLSSFIX | O38: 233 | P38: false | R38: 232814,39999999999000 RUB*1000 > RUB*1000;
A39: BA090_08 | B39: 90.1010000 | C39: m15041130 | D39: Прокат медный | E39: 653385, 654714 | F39: 12399 | G39: ООО "ЧЕДЕМ" | H39: 122927 | I39: ЧЕДЕМ ООО | J39: RUB*1000 | K39: NONE | L39: 111 | M39: 2022 | N39: SLSSFIX | O39: 3058 | P39: false | R39: 2025193,41999999990000 + 1032854,28000000000000 RUB*1000 > RUB*1000;
A40: BA090_08 | B40: 90.1010000 | C40: m15041130 | D40: Прокат медный | E40: 652747, 652748, 653728, 655456, 655457, 659374, 659774, 659778, 659782, 660270 | F40: 12408 | G40: ООО "КОМПАНИЯ ЭКОПРОЕКТ" | H40: 163963 | I40: КОМПАНИЯ ЭКОПРОЕКТ ООО | J40: RUB*1000 | K40: NONE | L40: 111 | M40: 2022 | N40: SLSSFIX | O40: 962 | P40: false | R40: 229068,00000000000000 + 226886,39999999999000 + 31047,00000000000000 + 188344,79999999999000 + 218160,00000000000000 + 8977,60000000000040 + 20565,66999999999800 + 9461,70000000000070 + 15679,50000000000000 + 13418,40000000000000 RUB*1000 > RUB*1000;
A41: BA090_08 | B41: 90.1010000 | C41: m15041130 | D41: Прокат медный | E41: 650303 | F41: 12414 | G41: ООО "ЭМС" | H41: 194923 | I41: ЭМС ООО | J41: RUB*1000 | K41: NONE | L41: 111 | M41: 2022 | N41: SLSSFIX | O41: 2208 | P41: false | R41: 2208450,39999999990000 RUB*1000 > RUB*1000;
A42: BA090_08 | B42: 90.1010000 | C42: m15041130 | D42: Прокат медный | E42: 652766 | F42: 12418 | G42: ООО "Завод КОНОРД" | H42: 195092 | I42: ЗАВОД КОНОРД ООО | J42: RUB*1000 | K42: NONE | L42: 111 | M42: 2022 | N42: SLSSFIX | O42: 1871 | P42: false | R42: 1870616,45000000000000 RUB*1000 > RUB*1000;
A43: BA090_08 | B43: 90.1010000 | C43: m15041130 | D43: Прокат медный | E43: 673554 | F43: 12423 | G43: РПХ ООО | H43: 208524 | I43: РПХ ООО | J43: RUB*1000 | K43: NONE | L43: 111 | M43: 2022 | N43: SLSSFIX | O43: 17 | P43: false | R43: 16823,66999999999800 RUB*1000 > RUB*1000;
A44: BA090_08 | B44: 90.1010000 | C44: m15041130 | D44: Прокат медный | E44: 652683, 652705, 654947, 654948, 654949 | F44: 12426 | G44: ООО "СТРИМ МЕХАНИК" | H44: 208667 | I44: СТРИМ МЕХАНИК ООО | J44: RUB*1000 | K44: NONE | L44: 111 | M44: 2022 | N44: SLSSFIX | O44: 7509 | P44: false | R44: 1082832,00000000000000 + 4335667,00000000000000 + 460620,15999999997000 + 745972,80000000005000 + 883536,00000000000000 RUB*1000 > RUB*1000;
A45: BA090_08 | B45: 90.1010000 | C45: m15041130 | D45: Прокат медный | E45: 651078, 651214, 651221, 651227, 651230, 651244, 652347, 652384, 652385, 708583 | F45: 12428 | G45: ООО "ЭЛЕКТРОН" | H45: 208696 | I45: ЭЛЕКТРОН ООО | J45: RUB*1000 | K45: NONE | L45: 111 | M45: 2022 | N45: SLSSFIX | O45: 6700 | P45: false | R45: 2519493,00000000000000 + 377659,20000000001000 + 469892,79999999999000 + 581445,80000000005000 + 1254477,91999999990000 + 614973,76000000001000 + 308670,96000000002000 + 191780,16000000000000 + 183594,72000000000000 + 198489,20000000001000 RUB*1000 > RUB*1000;
A46: BA090_08 | B46: 90.1010000 | C46: m15041130 | D46: Прокат медный | E46: 653146, 653147, 653300 | F46: 12434 | G46: ООО "ЗАВОД СИСТЕМ ОХЛАЖДЕНИЯ" | H46: 208959 | I46: ЗАВОД СИСТЕМ ОХЛАЖДЕНИЯ ООО | J46: RUB*1000 | K46: NONE | L46: 111 | M46: 2022 | N46: SLSSFIX | O46: 9374 | P46: false | R46: 5251103,21999999970000 + 1516848,91999999990000 + 2606252,10000000010000 RUB*1000 > RUB*1000;
A47: BA090_08 | B47: 90.1010000 | C47: m15041130 | D47: Прокат медный | E47: 651214, 651228, 651288, 653131, 653191, 653223, 709683 | F47: 12437 | G47: ОДО "СПЕЦМЕТПОСТАВКА" | H47: 209031 | I47: СПЕЦМЕТПОСТАВКА ОДО | J47: RUB*1000 | K47: NONE | L47: 111 | M47: 2022 | N47: SLSSFIX | O47: 2733 | P47: false | R47: 290404,79999999999000 + 190765,98000000001000 + 308731,02000000002000 + 891565,40000000002000 + 174012,39999999999000 + 174012,39999999999000 + 703891,19999999995000 RUB*1000 > RUB*1000;
A48: BA090_08 | B48: 90.1010000 | C48: m15041130 | D48: Прокат медный | E48: 680196, 709334 | F48: 12757 | G48: ОАО НПО "Электротерм" | H48: 186863 | I48: НПО ЭЛЕКТРОТЕРМ ОАО | J48: RUB*1000 | K48: NONE | L48: 111 | M48: 2022 | N48: SLSSFIX | O48: -1989 | P48: false | R48: -1288594,36000000010000 + -700550,40000000002000 RUB*1000 > RUB*1000;
A49: BA090_08 | B49: 90.1010000 | C49: m15041130 | D49: Прокат медный | E49: 653735, 658934, 659781, 659782, 660275, 660279, 660282, 673554, 650416 | F49: 2371 | G49: Физ.лицо | H49: 1000000 | I49: Физ.лицо | J49: RUB*1000 | K49: NONE | L49: 111 | M49: 2022 | N49: SLSSFIX | O49: 1197 | P49: false | R49: 20722,29999999999900 + 42724,57000000000000 + 95925,67999999999300 + 380184,37000000000000 + 34853,27999999999900 + 228068,57999999999000 + 26069,18000000000000 + 137419,67999999999000 + 231397,20000000001000 RUB*1000 > RUB*1000;
A50: BA090_08 | B50: 90.1010000 | C50: m15041130 | D50: Прокат медный | E50: 650781, 650783, 651576, 651205, 654027, 654028, 654096, 649926, 649927, 649928, 649934, 649936, 649937, 649940, 649943, 649944, 649946, 649951, 649968, 650018, 650043, 650047, 650053, 650055, 650126, 650279, 650302, 650303, 650421, 650436, 650514, 651031, 651042, 651202, 651210, 651228, 651244, 651250, 651283, 651286, 651289, 651353, 652106, 652114, 652120, 652799, 652889, 652890, 652899, 653198, 653224, 653229, 653837, 653841, 656171, 657225, 658765, 673831, 653630, 650044, 650550, 651275, 651281, 652335, 654719, 654150, 659028, 650962, 650968, 650969, 650974, 654159, 654163, 654165, 652651, 650286, 650296, 650304, 650305, 650309, 650330, 650630, 650631, 650635, 650636, 651050, 651056, 651110, 651278, 652111, 653018, 653022, 709669, 656559, 650852, 651823, 651247, 651249, 650050, 656995, 658690, 658691, 658706, 652405, 651072, 652127, 652128, 651068, 652126, 650772, 651214, 651221, 653204, 653343, 653355, 656790, 659123, 652298, 658103, 658104, 707047, 650138, 650465, 650466, 650469, 650813, 650971, 651207, 652147, 652326, 652340, 653911, 652272, 636709, 707328, 651025, 658762, 659610, 651701, 653277, 695372, 653734, 656363, 656372, 673546, 659040, 650729, 651057, 651125, 651126, 651127, 651128, 651129, 653040, 653042, 653043, 678935, 678936, 677414, 650155, 653840, 653063, 675601, 650270, 651322, 694241, 651029, 652323, 651711, 651724, 652748, 659516, 653196, 653197, 651571, 650682, 656041, 650378, 652690, 652906, 650990, 705868, 653723, 659366, 659778, 660275, 660277, 660278, 660280, 698976, 652442, 653414, 656522, 656523, 657816, 650318, 650866, 650827, 652039, 680196, 709334 | F50: 2562 | G50: Покупатели проката ЦМ (внут.рынок) | H50: 377 | I50: НПФ БИТЕК ООО | J50: RUB*1000 | K50: NONE | L50: 111 | M50: 2022 | N50: SLSSFIX | O50: 227837 | P50: false | R50: 415527,20000000001000 + 908247,19999999995000 + 326004,00000000000000 + 241716,22000000000000 + 1907246,52000000000000 + 2922665,06000000010000 + 226916,72000000000000 + 401936,59999999998000 + 375879,96000000002000 + 18132761,39999999900000 + 255723,82000000001000 + 254613,10000000001000 + 234328,60000000001000 + 261461,70000000001000 + 147542,39999999999000 + 492061,38000000000000 + 254284,32000000001000 + 357633,35999999999000 + 2133647,62000000010000 + 1362868,63999999990000 + 272227,77000000002000 + 1975393,00000000000000 + 260790,79999999999000 + 157248,00000000000000 + 268834,82000000001000 + 161951,07999999999000 + 418331,12000000000000 + 559904,64000000001000 + 277413,28000000003000 + 194111,66000000000000 + 188801,92000000001000 + 165262,72000000000000 + 291640,54999999999000 + 2280442,16999999990000 + 213596,92000000001000 + 608366,62000000000000 + 660649,60999999999000 + 474756,16999999998000 + 1718620,96000000000000 + 1755065,37999999990000 + 582527,52000000002000 + 3535066,66999999990000 + 126846,72000000000000 + 586287,28000000003000 + 268691,50000000000000 + 36796347,89999999900000 + 523617,98999999999000 + 5063889,96000000000000 + 7700588,94000000040000 + 13888587,72000000100000 + 665184,95999999996000 + 301652,38000000000000 + 610329,89000000001000 + 193507,64999999999000 + 193552,73999999999000 + 1395532,15999999990000 + 3931831,64000000010000 + 1776848,43999999990000 + 194111,66000000000000 + 172112,00000000000000 + 277094,40000000002000 + 882659,19999999995000 + 187260,00000000000000 + 195686,70000000001000 + 196872,67999999999000 + 1264005,00000000000000 + 767698,40000000002000 + 1540492,80000000000000 + 667938,19999999995000 + 326118,70000000001000 + 332922,38000000000000 + 338090,56000000000000 + 450220,44000000000000 + 663227,95999999996000 + 657601,83999999997000 + 711495,40000000002000 + 395995,59999999998000 + 291431,08000000002000 + 180057,14999999999000 + 620605,43999999994000 + 94149,60000000000600 + 178806,32000000001000 + 353495,03999999998000 + 914519,35999999999000 + 1337218,82000000010000 + 1579998,96000000000000 + 2450198,87999999990000 + 301880,79999999999000 + 379941,59999999998000 + 239535,42999999999000 + 881657,93000000005000 + 280879,64000000001000 + 130713,60000000001000 + 1974317,43999999990000 + 173714,22000000000000 + 193485,60000000001000 + 283410,64000000001000 + 288650,64000000001000 + 230584,00000000000000 + 594844,40000000002000 + 91131,03999999999400 + 542922,80000000005000 + 581472,81999999995000 + 599894,30000000005000 + 603482,90000000002000 + 604679,09999999998000 + 305332,63000000000000 + 883569,59999999998000 + 303269,40000000002000 + 432021,59999999998000 + 321455,79999999999000 + 316302,20000000001000 + 2992542,29999999980000 + 596960,00000000000000 + 307540,79999999999000 + 301438,79999999999000 + 305100,00000000000000 + 303879,59999999998000 + 296557,20000000001000 + 297604,50000000000000 + 598200,00000000000000 + 3438987,20000000020000 + 13993049,60000000000000 + -100930,56000000000000 + 872720,31999999995000 + 674987,04000000004000 + 516960,59999999998000 + 196079,39999999999000 + 197608,79999999999000 + 1463692,80000000000000 + 934193,40000000002000 + 217463,39999999999000 + 355364,34999999998000 + 284803,20000000001000 + 289396,79999999999000 + 186533,20000000001000 + 168572,76000000001000 + 481850,09999999998000 + 574200,00000000000000 + 229829,60000000001000 + 635648,00000000000000 + 424600,00000000000000 + 1957351,20000000000000 + 189982,79999999999000 + 625553,40000000002000 + 258986,39999999999000 + 432870,40000000002000 + 88475,19999999999700 + 662193,91000000003000 + 569704,58999999997000 + 24767,68999999999900 + 21408,95999999999900 + 231360,57000000001000 + 11471,98000000000000 + 1867680,80000000000000 + 318761,59999999998000 + 674827,19999999995000 + 200185,20000000001000 + 2430608,52999999980000 + 652662,00000000000000 + 639738,00000000000000 + 314053,20000000001000 + 668170,80000000005000 + 651369,59999999998000 + 324392,40000000002000 + 334731,59999999998000 + 338608,79999999999000 + 707454,54000000004000 + 336024,00000000000000 + 307591,20000000001000 + 396248,79999999999000 + 1381111,20000000000000 + 405323,20000000001000 + 586314,30000000005000 + 593061,30000000005000 + 192567,60000000001000 + 200797,20000000001000 + 868346,00000000000000 + 1215518,39999999990000 + 636059,80000000005000 + 302716,79999999999000 + 341760,59999999998000 + 348422,59999999998000 + 249662,39999999999000 + 1017844,40000000000000 + 1377083,60000000010000 + 404389,20000000001000 + -3577,19999999999980 + 359532,40000000002000 + 3313683,27999999980000 + 426879,20000000001000 + 1437904,80000000000000 + 956206,00000000000000 + 320279,40000000002000 + 205128,00000000000000 + 389417,59999999998000 + 331646,79999999999000 + 857976,30000000005000 + 165564,00000000000000 + 158468,39999999999000 + 79137,00000000000000 + 64482,00000000000000 + 182894,39999999999000 + 247754,70000000001000 + 891912,68000000005000 + 786211,67000000004000 + 377908,79999999999000 + 370696,79999999999000 + 372139,20000000001000 + 681469,19999999995000 + 236741,20000000001000 + 223669,60000000001000 + 201650,79999999999000 + 1288594,36000000010000 + 700550,40000000002000 + 1400041,50000000000000 RUB*1000 > RUB*1000;
A51: BA090_08 | B51: 90.1010000 | C51: m15041130 | D51: Прокат медный | E51: 655572, 650144, 650146, 650169, 650468, 650471, 650473, 650475, 650476, 650479, 650622, 650625, 650831, 650899, 650911, 651077, 651207, 651214, 651221, 651228, 651235, 651244, 651250, 651265, 651272, 651275, 651278, 651281, 651288, 651292, 651663, 651692, 651703, 651708, 651711, 651713, 651714, 651722, 651723, 651724, 652025, 652039, 652054, 652146, 652356, 652369, 652386, 652392, 652405, 652540, 652748, 652751, 653180, 653186, 653191, 653198, 653343, 653355, 654024, 654879, 670615, 685511, 685512, 709030 | F51: 2814 | G51: ООО "Промэко" | H51: 65765 | I51: ПРОМЭКО ООО | J51: RUB*1000 | K51: NONE | L51: 111 | M51: 2022 | N51: SLSSFIX | O51: 50913 | P51: false | R51: 17254885,19999999900000 + 748941,19999999995000 + 734181,59999999998000 + 169961,60000000001000 + 346605,00000000000000 + 529360,80000000005000 + 347618,40000000002000 + 345284,59999999998000 + 167832,00000000000000 + 591384,00000000000000 + 454484,79999999999000 + 202938,39999999999000 + 75004,80000000000300 + 210327,48000000001000 + 877426,76000000001000 + 190704,00000000000000 + 2156980,00000000000000 + 1997514,80000000000000 + 3766150,79999999980000 + 556026,90000000002000 + 1212511,72000000000000 + 379431,35999999999000 + 1043472,24000000000000 + 314952,29999999999000 + 178084,79999999999000 + 178084,79999999999000 + 652711,19999999995000 + 484593,84000000003000 + 391496,46000000002000 + 186451,20000000001000 + 75004,80000000000300 + 508446,00000000000000 + 21636,00000000000000 + 152894,39999999999000 + 193281,60000000001000 + 47599,19999999999700 + 73562,39999999999400 + 312934,79999999999000 + 1089330,00000000000000 + 1497333,60000000010000 + 357822,50000000000000 + 182280,00000000000000 + 426522,79999999999000 + 175844,20000000001000 + 261835,20000000001000 + 805983,12000000000000 + 418618,79999999999000 + 451367,28000000003000 + 421833,76000000001000 + 177146,45999999999000 + 380275,20000000001000 + 346605,00000000000000 + 639739,94999999995000 + 236887,20000000001000 + 176475,20000000001000 + 1524591,20000000000000 + 302091,00000000000000 + 589227,00000000000000 + 298576,79999999999000 + 1077935,20000000000000 + 124009,60000000001000 + 391008,79999999999000 + 388024,00000000000000 + 40813,44999999999700 RUB*1000 > RUB*1000;
A52: BA090_08 | B52: 90.1010000 | C52: m15041130 | D52: Прокат медный | E52: 650765, 651076, 651077, 651207, 651214, 651244, 651250, 651335, 652138, 652146, 652618, 653149, 653150, 653186, 658082 | F52: 2910 | G52: НАО ПКП "РОСТЕХКОМ" | H52: 19717 | I52: НАО ПКП РОСТЕХКОМ | J52: RUB*1000 | K52: NONE | L52: 111 | M52: 2022 | N52: SLSSFIX | O52: 3680 | P52: false | R52: 241242,00000000000000 + 197964,79999999999000 + 273504,00000000000000 + 177363,20000000001000 + 178263,60000000001000 + 141593,94000000000000 + 186219,66000000000000 + 38284,80000000000300 + 206460,00000000000000 + 197267,39999999999000 + 517862,79999999999000 + 353183,76000000001000 + 209664,72000000000000 + 178561,60000000001000 + 582870,59999999998000 RUB*1000 > RUB*1000;
A53: BA090_08 | B53: 90.1010000 | C53: m15041130 | D53: Прокат медный | E53: 656527, 657820, 683102, 687672 | F53: 3086 | G53: ЗАО Атлант | H53: 112187 | I53: АТЛАНТ ЗАО | J53: RUB*1000 | K53: NONE | L53: 111 | M53: 2022 | N53: SLSSFIX | O53: 10306 | P53: false | R53: 504335,20000000001000 + 9116958,80000000070000 + 306445,40000000002000 + 377971,20000000001000 RUB*1000 > RUB*1000;
A54: BA090_08 | B54: 90.1010000 | C54: m15041130 | D54: Прокат медный | E54: 694324, 651214, 651221, 651228, 653191, 653198, 687729, 651564, 707242, 652596, 652606 | F54: 3123 | G54: Покупатели проката ЦМ (экспорт) | H54: 212145 | I54: CGR TRANSILVANIA SRL | J54: RUB*1000 | K54: NONE | L54: 111 | M54: 2022 | N54: SLSSFIX | O54: 18478 | P54: false | R54: 9618606,26999999960000 + 176177,60000000001000 + 179724,79999999999000 + 182621,67999999999000 + 174995,20000000001000 + 179724,79999999999000 + 4775043,00000000000000 + 406086,00000000000000 + 1942908,00000000000000 + 432586,00000000000000 + 409732,40000000002000 RUB*1000 > RUB*1000;
A55: BA090_08 | B55: 90.1010000 | C55: m15041130 | D55: Прокат медный | E55: 653655, 654724, 657874, 659774, 659778, 659782 | F55: 352 | G55: АО "Уралэлектромедь" | H55: 6 | I55: УРАЛЭЛЕКТРОМЕДЬ АО | J55: RUB*1000 | K55: NONE | L55: 111 | M55: 2022 | N55: SLSSFIX | O55: 8215 | P55: false | R55: 2792008,29000000000000 + 332280,26000000001000 + 5052066,59999999960000 + 8512,00000000000000 + 23702,40000000000100 + 6171,19999999999980 RUB*1000 > RUB*1000;
A56: BA090_08 | B56: 90.1010000 | C56: m15041130 | D56: Прокат медный | E56: 659130 | F56: 353 | G56: АО "Святогор" | H56: 344 | I56: СВЯТОГОР АО | J56: RUB*1000 | K56: NONE | L56: 111 | M56: 2022 | N56: SLSSFIX | O56: 980 | P56: false | R56: 980045,19999999995000 RUB*1000 > RUB*1000;
A57: BA090_08 | B57: 90.1010000 | C57: m15041130 | D57: Прокат медный | E57: 650667, 650669, 650670, 650673, 650675, 650676, 651322, 653125 | F57: 362 | G57: АО "Шадринский автоагрегатный завод" | H57: 637 | I57: ШААЗ АО | J57: RUB*1000 | K57: NONE | L57: 111 | M57: 2022 | N57: SLSSFIX | O57: 9403 | P57: false | R57: 183945,22000000000000 + 879370,76000000001000 + 3049642,75999999980000 + 585047,92000000004000 + 163701,25000000000000 + 2912561,83000000010000 + 158188,32000000001000 + 1470857,86000000010000 RUB*1000 > RUB*1000;
A58: BA090_08 | B58: 90.1010000 | C58: m15041130 | D58: Прокат медный | E58: 650851, 651822 | F58: 4438 | G58: ООО "Автокомпоненты - Группа ГАЗ" | H58: 74798 | I58: АВТОКОМПОНЕНТЫ - ГРУППА ГАЗ ООО | J58: RUB*1000 | K58: NONE | L58: 111 | M58: 2022 | N58: SLSSFIX | O58: 1099 | P58: false | R58: 531124,52000000002000 + 567903,00000000000000 RUB*1000 > RUB*1000;
A59: BA090_08 | B59: 90.1010000 | C59: m15041130 | D59: Прокат медный | E59: 651024, 652063 | F59: 4444 | G59: ООО "ЗМИ - Профит" | H59: 125817 | I59: ЗМИ - ПРОФИТ ООО | J59: RUB*1000 | K59: NONE | L59: 111 | M59: 2022 | N59: SLSSFIX | O59: 10627 | P59: false | R59: 5432158,88999999970000 + 5194692,69000000040000 RUB*1000 > RUB*1000;
A60: BA090_08 | B60: 90.1010000 | C60: m15041130 | D60: Прокат медный | E60: 653178, 654746, 654750, 659955, 659957, 687190, 709343, 709682 | F60: 4452 | G60: АО "СИЛОВЫЕ МАШИНЫ" | H60: 66834 | I60: СИЛОВЫЕ МАШИНЫ АО | J60: RUB*1000 | K60: NONE | L60: 111 | M60: 2022 | N60: SLSSFIX | O60: 9577 | P60: false | R60: 1055553,63999999990000 + 639484,80000000005000 + 2908237,43000000020000 + 2534004,06000000010000 + 687008,40000000002000 + 99703,88999999999900 + 1537054,20000000000000 + 115999,20000000000000 RUB*1000 > RUB*1000;
A61: BA090_08 | B61: 90.1010000 | C61: m15041130 | D61: Прокат медный | E61: 660099, 660103, 650692, 651065, 656881, 659613, 660013, 660014, 660090, 660093, 660094, 681702, 684077, 709366 | F61: 4457 | G61: ООО "Профикс" | H61: 125887 | I61: ПРОФИКС ООО | J61: RUB*1000 | K61: NONE | L61: 111 | M61: 2022 | N61: SLSSFIX | O61: 60863 | P61: false | R61: 948974,00000000000000 + 628380,00000000000000 + 3787901,79999999980000 + 1132503,06000000010000 + 4331789,00000000000000 + 30480190,87000000100000 + 1451616,61000000010000 + 1651022,13999999990000 + 2149134,83999999990000 + 1061857,43999999990000 + 5112148,23000000040000 + 1008865,04000000000000 + 1240094,24000000000000 + 5075773,71999999970000 + 802793,47999999998000 RUB*1000 > RUB*1000;
A62: BA090_08 | B62: 90.1010000 | C62: m15041130 | D62: Прокат медный | E62: 650046, 651014, 652110, 652118, 654559 | F62: 4460 | G62: ООО "Сибэлектропривод" | H62: 47853 | I62: СИБЭЛЕКТРОПРИВОД ООО | J62: RUB*1000 | K62: NONE | L62: 111 | M62: 2022 | N62: SLSSFIX | O62: 18544 | P62: false | R62: 9717474,00000000000000 + 201360,00000000000000 + 2107568,00000000000000 + 5831385,59999999960000 + 685966,40000000002000 RUB*1000 > RUB*1000;
A63: BA090_08 | B63: 90.1010000 | C63: m15041130 | D63: Прокат медный | E63: 651076, 651078, 651207, 651214, 651235, 651250, 651275, 651281, 651284, 651288, 651292, 652039, 652052, 652326, 652340, 652356, 652369, 652405, 653151, 653190, 653191, 653195, 653198, 653207, 653216, 653223, 653228, 653230, 653350, 653355, 653363, 655592, 656990 | F63: 4471 | G63: ООО "Галактика" | H63: 60001 | I63: ГАЛАКТИКА ООО | J63: RUB*1000 | K63: NONE | L63: 111 | M63: 2022 | N63: SLSSFIX | O63: 28241 | P63: false | R63: 336470,40000000002000 + 336470,40000000002000 + 1141574,15999999990000 + 3110664,96000000000000 + 1991670,82000000010000 + 298905,42999999999000 + 1443169,08000000010000 + 310817,23999999999000 + 2498938,25000000000000 + 835595,94999999995000 + 312499,70000000001000 + 144774,00000000000000 + 325580,64000000001000 + 294802,79999999999000 + 506853,94000000000000 + 2385840,14999999990000 + 480807,10999999999000 + 585742,19999999995000 + 437391,35999999999000 + 310318,73999999999000 + 4351939,91999999990000 + 316550,03999999998000 + 299865,00000000000000 + 434820,10999999999000 + 313059,06000000000000 + 1191424,56000000010000 + 892862,88000000000000 + 329324,21000000002000 + 183823,35000000001000 + 586835,81000000006000 + 734489,32999999996000 + 212903,34000000000000 + 304230,40000000002000 RUB*1000 > RUB*1000;
A64: BA090_08 | B64: 90.1010000 | C64: m15041130 | D64: Прокат медный | E64: 650138, 650139, 650210, 650231, 650234, 650250, 650465, 650466, 650467, 650469, 650470, 650971, 651214, 651221, 651228, 651244, 651272, 651275, 651278, 652356, 653190, 653223, 653228, 669968 | F64: 4480 | G64: ООО "ПРИМА-ЦЕНТР" | H64: 67106 | I64: ПРИМА-ЦЕНТР ООО | J64: RUB*1000 | K64: NONE | L64: 111 | M64: 2022 | N64: SLSSFIX | O64: 10588 | P64: false | R64: 560372,40000000002000 + 1590967,20000000000000 + 415615,79999999999000 + 178791,00000000000000 + 1172986,20000000000000 + 307168,79999999999000 + 214917,60000000001000 + 430556,40000000002000 + 209869,20000000001000 + 215638,79999999999000 + 178136,39999999999000 + 635810,93999999994000 + 867042,00000000000000 + 419936,40000000002000 + 168692,39999999999000 + 313755,90000000002000 + 357364,79999999999000 + 417618,00000000000000 + 473299,20000000001000 + 552991,31999999995000 + 181852,79999999999000 + 179280,00000000000000 + 178084,79999999999000 + 367696,79999999999000 RUB*1000 > RUB*1000;
A65: BA090_08 | B65: 90.1010000 | C65: m15041130 | D65: Прокат медный | E65: 650478, 677232 | F65: 4488 | G65: ООО "ТД"ЦветКомплексМеталл" | H65: 18826 | I65: ТД ЦВЕТКОМПЛЕКСМЕТАЛЛ ООО | J65: RUB*1000 | K65: NONE | L65: 111 | M65: 2022 | N65: SLSSFIX | O65: 2403 | P65: false | R65: 376466,40000000002000 + 2026679,20000000000000 RUB*1000 > RUB*1000;
A66: BA090_08 | B66: 90.1010000 | C66: m15041130 | D66: Прокат медный | E66: 704242 | F66: 449 | G66: АО "Среднеуральский медеплавильный завод" | H66: 17 | I66: СУМЗ АО | J66: RUB*1000 | K66: NONE | L66: 111 | M66: 2022 | N66: SLSSFIX | O66: 242 | P66: false | R66: 241602,00000000000000 RUB*1000 > RUB*1000;
A67: BA090_08 | B67: 90.1010000 | C67: m15041130 | D67: Прокат медный | E67: 651827, 652783, 654065, 654073 | F67: 468 | G67: АО "Кировский завод ОЦМ" | H67: 677 | I67: КЗОЦМ АО | J67: RUB*1000 | K67: NONE | L67: 111 | M67: 2022 | N67: SLSSFIX | O67: 2692 | P67: false | R67: 1682546,78000000000000 + 425580,56000000000000 + 292471,78000000003000 + 291359,71999999997000 RUB*1000 > RUB*1000;
A68: BA090_08 | B68: 90.1010000 | C68: m15041130 | D68: Прокат медный | E68: 409225, 417930, 417984, 650666, 652302, 652303, 653153, 653156, 653158, 656993, 658015 | F68: 471 | G68: ООО "Оренбургский радиатор" | H68: 14895 | I68: ОРЕНБУРГСКИЙ РАДИАТОР ООО | J68: RUB*1000 | K68: NONE | L68: 111 | M68: 2022 | N68: SLSSFIX | O68: 9359 | P68: false | R68: 173931,84000000000000 + 273751,03999999998000 + 163403,84000000000000 + 409889,04999999999000 + 1347368,39999999990000 + 390292,28000000003000 + 1835328,35000000010000 + 697504,43000000005000 + 1019901,06000000010000 + 2057850,38999999990000 + 989354,81999999995000 RUB*1000 > RUB*1000;
A69: BA090_08 | B69: 90.1010000 | C69: m15041130 | D69: Прокат медный | E69: 651808 | F69: 7223 | G69: ПАО "АВТОДИЗЕЛЬ" (ЯМЗ) | H69: 1790 | I69: АВТОДИЗЕЛЬ (ЯМЗ) ПАО | J69: RUB*1000 | K69: NONE | L69: 111 | M69: 2022 | N69: SLSSFIX | O69: 1121 | P69: false | R69: 1120927,20000000000000 RUB*1000 > RUB*1000;
A70: BA090_08 | B70: 90.1010000 | C70: m15041130 | D70: Прокат медный | E70: 650142, 650144, 650146, 650800, 651082, 651207, 651214, 651221, 651228, 651235, 651244, 651250, 651275, 651281, 651284, 651288, 651292, 651647, 651672, 651723, 651724, 652039, 652045, 652347, 652356, 652369, 652386, 652405, 652465, 652748, 653186, 653190, 653191, 653195, 653198, 653204, 653216, 653228, 653343, 653350, 653355, 653363, 653611, 653615, 653957, 654877, 654886 | F70: 7247 | G70: ООО "Металлсервис-Москва" | H70: 123329 | I70: МЕТАЛЛСЕРВИС-МОСКВА ООО | J70: RUB*1000 | K70: NONE | L70: 111 | M70: 2022 | N70: SLSSFIX | O70: 58625 | P70: false | R70: 413693,00000000000000 + 2473371,60000000010000 + 950395,59999999998000 + 145682,39999999999000 + 630688,80000000005000 + 2083233,60000000010000 + 4170052,79999999980000 + 5050915,20000000020000 + 2122974,00000000000000 + 2122376,39999999990000 + 2897164,79999999980000 + 1313166,24000000000000 + 778075,19999999995000 + 2344922,64000000010000 + 749091,59999999998000 + 475689,59999999998000 + 1491251,04000000000000 + 486088,79999999999000 + 335228,40000000002000 + 650587,19999999995000 + 981106,40000000002000 + 516313,59999999998000 + 305418,79999999999000 + 3290304,72000000020000 + 1469319,12000000010000 + 693275,76000000001000 + 939606,47999999998000 + 1174523,04000000000000 + 955666,56000000006000 + 1339713,20000000000000 + 1211932,80000000000000 + 181670,39999999999000 + 2359324,79999999980000 + 910742,40000000002000 + 1193404,80000000000000 + 584452,80000000005000 + 595209,59999999998000 + 470711,20000000001000 + 2233885,75999999980000 + 698099,40000000002000 + 1951857,26000000000000 + 1470555,06000000010000 + 285330,59999999998000 + 294786,00000000000000 + 79632,80000000000300 + 190220,39999999999000 + 562874,40000000002000 RUB*1000 > RUB*1000;
A71: BA090_08 | B71: 90.1010000 | C71: m15041130 | D71: Прокат медный | E71: 657228 | F71: 8130 | G71: АО "ПТФК "ЗТЭО" | H71: 109293 | I71: ПТФК ЗТЭО АО | J71: RUB*1000 | K71: NONE | L71: 111 | M71: 2022 | N71: SLSSFIX | O71: 1329 | P71: false | R71: 1328514,60000000010000 RUB*1000 > RUB*1000;
A72: BA090_08 | B72: 90.1010000 | C72: m15041130 | D72: Прокат медный | E72: 654156 | F72: 8138 | G72: БЕЛТЕЛЕКАБЕЛЬ СЗАО | H72: 115595 | I72: БЕЛТЕЛЕКАБЕЛЬ СЗАО | J72: RUB*1000 | K72: NONE | L72: 111 | M72: 2022 | N72: SLSSFIX | O72: 658 | P72: false | R72: 657514,38000000000000 RUB*1000 > RUB*1000;
A73: BA090_08 | B73: 90.1010000 | C73: m15041130 | D73: Прокат медный | E73: 652430, 696402 | F73: 8207 | G73: АО "КОНТАКТОР" | H73: 21780 | I73: КОНТАКТОР АО | J73: RUB*1000 | K73: NONE | L73: 111 | M73: 2022 | N73: SLSSFIX | O73: 520 | P73: false | R73: 186894,39999999999000 + 333349,59999999998000 RUB*1000 > RUB*1000;
A74: BA090_08 | B74: 90.1010000 | C74: m15041130 | D74: Прокат медный | E74: 654697 | F74: 8984 | G74: ООО "МРК" | H74: 134897 | I74: МРК ООО | J74: RUB*1000 | K74: NONE | L74: 111 | M74: 2022 | N74: SLSSFIX | O74: 2303 | P74: false | R74: 2302549,33999999990000 RUB*1000 > RUB*1000;
A75: BA090_08 | B75: 90.1010000 | C75: m15041130 | D75: Прокат медный | E75: 649926, 649981, 650965, 650998, 651244, 651250, 652033, 652386 | F75: 9523 | G75: АО "УЭТМ" | H75: 67544 | I75: УЭТМ АО | J75: RUB*1000 | K75: NONE | L75: 111 | M75: 2022 | N75: SLSSFIX | O75: 1957 | P75: false | R75: 198504,60000000001000 + 191716,20000000001000 + 205324,98000000001000 + 197516,20000000001000 + 217858,39999999999000 + 328559,34000000003000 + 206703,00000000000000 + 411109,29999999999000 RUB*1000 > RUB*1000;
A76: BA090_08 | B76: 90.1010000 | C76: m15041130 | D76: Прокат медный | E76: 650138, 650139, 650312, 650313, 650351, 650465, 650466, 650467, 650684, 650687, 650811, 650902, 650965, 650966, 650981, 651058, 651121, 651167, 651183, 651207, 651214, 651221, 651228, 651235, 651236, 651247, 651249, 651543, 651701, 651723, 651724, 651727, 652013, 652066, 652185, 652188, 652274, 652416, 652747, 652748, 652751, 653190, 653191, 653198, 653221, 653228, 653294, 654000, 654016, 654024, 655370, 655592, 657867, 659516, 659517, 672984, 691091, 693092, 693171, 709681, 709684, 709685, 709686 | F76: 9940 | G76: ООО "ФОЛКОН" | H76: 115562 | I76: ФОЛКОН ООО | J76: RUB*1000 | K76: NONE | L76: 111 | M76: 2022 | N76: SLSSFIX | O76: 31774 | P76: false | R76: 337155,00000000000000 + 404586,00000000000000 + 182460,00000000000000 + 312614,79999999999000 + 304459,64000000001000 + 619651,40000000002000 + 395595,20000000001000 + 1577788,80000000000000 + 588542,06000000006000 + 183676,39999999999000 + 197399,79999999999000 + 182437,20000000001000 + 2788311,68999999990000 + 313939,87000000000000 + 185926,73999999999000 + 942054,30000000005000 + 616535,04000000004000 + 499020,79999999999000 + 307564,79999999999000 + 787636,80000000005000 + 1155758,39999999990000 + 294019,20000000001000 + 188244,00000000000000 + 256908,23999999999000 + 429501,59999999998000 + 516253,84999999998000 + 1316065,67999999990000 + 229829,60000000001000 + 1551690,20000000000000 + 36781,19999999999700 + 346605,00000000000000 + 277284,00000000000000 + 337750,21999999997000 + 225501,20000000001000 + 360914,40000000002000 + 538865,19999999995000 + 248495,79999999999000 + 527549,76000000001000 + 341983,59999999998000 + 1227381,00000000000000 + 344624,40000000002000 + 408960,00000000000000 + 1204761,60000000010000 + 465228,00000000000000 + 184245,60000000001000 + 178263,60000000001000 + 302385,59999999998000 + 303760,59999999998000 + 201650,79999999999000 + 223572,00000000000000 + 43932,00000000000000 + 214557,35000000001000 + 336747,59999999998000 + 502681,20000000001000 + 643555,80000000005000 + 1757984,80000000000000 + 602739,19999999995000 + 597181,68000000005000 + 181670,39999999999000 + 210566,39999999999000 + 220875,20000000001000 + 213475,20000000001000 + 295495,20000000001000 RUB*1000 > RUB*1000;
A77: BA090_08 | B77: 90.1010000 | C77: m15041130 | D77: Прокат медный | E77: 650331 | F77: 9942 | G77: ООО "ПРОИЗВОДСТВЕННАЯ КОМПАНИЯ "БОРЕЦ" ООО "ПК "БОРЕЦ" | H77: 31859 | I77: ПРОИЗВОДСТВЕННАЯ КОМПАНИЯ БОРЕЦ ООО | J77: RUB*1000 | K77: NONE | L77: 111 | M77: 2022 | N77: SLSSFIX | O77: 544 | P77: false | R77: 543526,71999999997000 RUB*1000 > RUB*1000;
A78: BA090_08 | B78: 90.1010000 | C78: m15041130 | D78: Прокат медный | E78: 651525 | F78: 9948 | G78: ПАО "ЭЛЕКТРОВЫПРЯМИТЕЛЬ" | H78: 123959 | I78: ЭЛЕКТРОВЫПРЯМИТЕЛЬ ПАО | J78: RUB*1000 | K78: NONE | L78: 111 | M78: 2022 | N78: SLSSFIX | O78: 387 | P78: false | R78: 386531,59999999998000 RUB*1000 > RUB*1000;
A79: BA090_08 | B79: 90.1010000 | C79: m15041130 | D79: Прокат медный | E79: 649985, 650200, 650204, 650207, 650209, 650221, 650223, 650227, 650230, 650233, 650235, 650236, 650245, 650249, 650251, 650263, 650265, 650266, 650545, 650588, 650589, 650592, 650608, 650911, 650913, 651228, 651244, 651275, 651278, 651469, 652039, 652335, 652356, 652369, 652372, 653190, 653191, 653198, 653216, 653343, 653350, 653355, 653363, 653370, 653621, 654903, 656691, 657878, 708625 | F79: 9950 | G79: ООО "ЛИСТ СПб" | H79: 69920 | I79: ЛИСТ СПБ ООО | J79: RUB*1000 | K79: NONE | L79: 111 | M79: 2022 | N79: SLSSFIX | O79: 33475 | P79: false | R79: 5498315,09999999960000 + 419719,20000000001000 + 1491764,39999999990000 + 413857,20000000001000 + 998283,00000000000000 + 978963,80000000005000 + 181135,79999999999000 + 711060,59999999998000 + 1057504,80000000000000 + 1978468,20000000000000 + 1667152,80000000000000 + 301306,79999999999000 + 305996,40000000002000 + 727176,19999999995000 + 296617,20000000001000 + 594406,80000000005000 + 179377,20000000001000 + 292513,79999999999000 + 184653,00000000000000 + 643647,59999999998000 + 485373,59999999998000 + 234480,00000000000000 + 324754,79999999999000 + 475941,20000000001000 + 73861,19999999999700 + 187347,60000000001000 + 197208,00000000000000 + 176889,60000000001000 + 890424,00000000000000 + 28355,59999999999900 + 193486,79999999999000 + 320313,59999999998000 + 649352,16000000003000 + 573994,80000000005000 + 650550,39000000001000 + 182865,60000000001000 + 180475,20000000001000 + 479275,20000000001000 + 51678,00000000000000 + 1783294,02000000000000 + 1893833,13999999990000 + 590893,81999999995000 + 745965,43999999994000 + 904015,40000000002000 + 262526,40000000002000 + 279573,20000000001000 + 111064,80000000000000 + 350737,20000000001000 + 1274439,60000000010000 RUB*1000 > RUB*1000;
A80: BA090_08 | B80: 90.1010000 | C80: m15041130 | D80: Прокат медный | E80: 650278, 651207, 651235, 651250, 651278, 651281, 651460, 652031, 652386, 652392, 652987, 653204, 653223, 653826 | F80: 9952 | G80: ООО "КЦМ" | H80: 69031 | I80: КЦМ ООО | J80: RUB*1000 | K80: NONE | L80: 111 | M80: 2022 | N80: SLSSFIX | O80: 6667 | P80: false | R80: 234848,39999999999000 + 478882,79999999999000 + 1222092,00000000000000 + 466135,56000000000000 + 308361,59999999998000 + 189140,39999999999000 + 217792,64000000001000 + 306107,06000000000000 + 628978,68000000005000 + 164163,78000000000000 + 1193896,60000000010000 + 695930,40000000002000 + 351388,79999999999000 + 209416,00000000000000 RUB*1000 > RUB*1000;
A81: BA090_08 | B81: 90.1010000 | C81: m15041130 | D81: Прокат медный | E81: 686155, 691842, 705155, 708267 | F81: 9953 | G81: ООО "МЕТАПРОМ СПб" | H81: 194940 | I81: МЕТАПРОМ СПБ ООО | J81: RUB*1000 | K81: NONE | L81: 111 | M81: 2022 | N81: SLSSFIX | O81: 4897 | P81: false | R81: 1922534,17999999990000 + 598312,01000000001000 + 963106,23999999999000 + 1412829,76000000000000 RUB*1000 > RUB*1000;
A82: BA090_08 | B82: 90.1010000 | C82: m15041130 | D82: Прокат медный | E82: 655445, 655451, 656624, 656630, 656641, 656650, 656659, 656665, 656682 | F82: 9954 | G82: АО "ЗЭТА" | H82: 76261 | I82: ЗЭТА АО | J82: RUB*1000 | K82: NONE | L82: 111 | M82: 2022 | N82: SLSSFIX | O82: 13578 | P82: false | R82: 989404,31999999995000 + 625359,00000000000000 + 1416648,00000000000000 + 2217500,79999999980000 + 2607387,04000000000000 + 2884464,14000000010000 + 535731,95999999996000 + 1814732,26000000000000 + 487047,47999999998000 RUB*1000 > RUB*1000;
A83: BA090_08 | B83: 90.1010000 | C83: m15041200 | D83: Прокат латунный | E83: 652516, 652522, 652951, 654646, 654647, 654654, 654655, 654656, 654659, 654660, 654662, 655787, 655802, 655803, 655818, 655819, 655826, 655848, 656060, 656062, 656082, 656083, 656092, 656300, 656319, 656919, 657073, 657091, 657093, 657094, 657098, 657099, 657101, 657102, 657103, 657105, 657106, 657108, 657329, 657336, 657349, 657357, 657393, 657406, 657486, 657487, 657491, 657492, 657495, 657496, 657557, 657573, 658039, 658062, 658067, 658184, 658195, 658722, 658726, 658727, 658729, 658734, 658735, 659208, 691233, 702449 | F83: 10723 | G83: ООО "АЛЬМЕТ" | H83: 126128 | I83: АЛЬМЕТ ООО | J83: RUB*1000 | K83: NONE | L83: 111 | M83: 2022 | N83: SLSSFIX | O83: 12575 | P83: false | R83: 191208,28000000000000 + 175383,67999999999000 + 150367,60000000001000 + 248103,60000000001000 + 249100,00000000000000 + 248103,60000000001000 + 510156,79999999999000 + 157182,10000000001000 + 246359,89999999999000 + 147467,20000000001000 + 157182,10000000001000 + 150880,79999999999000 + 157552,39999999999000 + 160118,39999999999000 + 153960,00000000000000 + 153960,00000000000000 + 161658,00000000000000 + 129839,60000000001000 + 242152,79999999999000 + 272062,88000000000000 + 224688,20000000001000 + 225734,42000000001000 + 160463,35999999999000 + 131084,79999999999000 + 118580,00000000000000 + 149854,39999999999000 + 156683,89999999999000 + 145474,39999999999000 + 152449,20000000001000 + 246110,79999999999000 + 149460,00000000000000 + 150456,39999999999000 + 250096,39999999999000 + 152449,20000000001000 + 252089,20000000001000 + 149460,00000000000000 + 151452,79999999999000 + 145474,39999999999000 + 197787,20000000001000 + 213824,00000000000000 + 131584,00000000000000 + 206422,39999999999000 + 129528,00000000000000 + 86352,00000000000000 + 207244,79999999999000 + 125004,80000000000000 + 126649,60000000001000 + 113491,20000000000000 + 206011,20000000001000 + 124182,39999999999000 + 123360,00000000000000 + 119248,00000000000000 + 236379,12000000000000 + 243603,92000000001000 + 239041,14999999999000 + 221225,60000000001000 + 237673,60000000001000 + 265217,85999999999000 + 261520,59000000000000 + 289110,38000000000000 + 271379,98999999999000 + 265562,94000000000000 + 258809,25000000000000 + 150545,22000000000000 + 173652,92000000001000 + 175383,67999999999000 RUB*1000 > RUB*1000;
A84: BA090_08 | B84: 90.1010000 | C84: m15041200 | D84: Прокат латунный | E84: 653577, 654400, 654445, 657478, 657493, 657557 | F84: 10846 | G84: ООО "ДВЗ" | H84: 125795 | I84: ДВЗ ООО | J84: RUB*1000 | K84: NONE | L84: 111 | M84: 2022 | N84: SLSSFIX | O84: 16701 | P84: false | R84: 180259,20000000001000 + 220633,20999999999000 + 548843,56999999995000 + 156415,39999999999000 + 15835121,60000000000000 + -240320,79999999999000 RUB*1000 > RUB*1000;
A85: BA090_08 | B85: 90.1010000 | C85: m15041200 | D85: Прокат латунный | E85: 656509 | F85: 10847 | G85: ЗАО "Мапра" | H85: 125824 | I85: МАПРА ЗАО | J85: RUB*1000 | K85: NONE | L85: 111 | M85: 2022 | N85: SLSSFIX | O85: 233 | P85: false | R85: 232909,60000000001000 RUB*1000 > RUB*1000;
A86: BA090_08 | B86: 90.1010000 | C86: m15041200 | D86: Прокат латунный | E86: 653509, 654341, 654543 | F86: 10853 | G86: ООО "МИАССМАШ" | H86: 194978 | I86: МИАССМАШ ООО | J86: RUB*1000 | K86: NONE | L86: 111 | M86: 2022 | N86: SLSSFIX | O86: 3033 | P86: false | R86: 1599009,20000000000000 + 525476,00000000000000 + 908610,00000000000000 RUB*1000 > RUB*1000;
A87: BA090_08 | B87: 90.1010000 | C87: m15041200 | D87: Прокат латунный | E87: 651943, 654234, 654237, 655736 | F87: 10858 | G87: МЕЛЬХИОР ООО | H87: 208504 | I87: МЕЛЬХИОР ООО | J87: RUB*1000 | K87: NONE | L87: 111 | M87: 2022 | N87: SLSSFIX | O87: 968 | P87: false | R87: 500225,20000000001000 + 154639,00000000000000 + 154639,00000000000000 + 158715,20000000001000 RUB*1000 > RUB*1000;
A88: BA090_08 | B88: 90.1010000 | C88: m15041200 | D88: Прокат латунный | E88: 657220 | F88: 10872 | G88: ООО "Тиара" | H88: 210031 | I88: ТИАРА ООО | J88: RUB*1000 | K88: NONE | L88: 111 | M88: 2022 | N88: SLSSFIX | O88: 211 | P88: false | R88: 211029,39999999999000 RUB*1000 > RUB*1000;
A89: BA090_08 | B89: 90.1010000 | C89: m15041200 | D89: Прокат латунный | E89: 655353, 655362 | F89: 10875 | G89: АО "ТЭМЗ" | H89: 5028 | I89: ТЭМЗ АО | J89: RUB*1000 | K89: NONE | L89: 111 | M89: 2022 | N89: SLSSFIX | O89: 3395 | P89: false | R89: 2017714,39999999990000 + 1377446,39999999990000 RUB*1000 > RUB*1000;
A90: BA090_08 | B90: 90.1010000 | C90: m15041200 | D90: Прокат латунный | E90: 655996 | F90: 10878 | G90: АО "НПЗ" | H90: 54455 | I90: НПЗ АО | J90: RUB*1000 | K90: NONE | L90: 111 | M90: 2022 | N90: SLSSFIX | O90: 1613 | P90: false | R90: 1612566,00000000000000 RUB*1000 > RUB*1000;
A91: BA090_08 | B91: 90.1010000 | C91: m15041200 | D91: Прокат латунный | E91: 654286 | F91: 10879 | G91: АО "ЭКСПОПУЛ" | H91: 67980 | I91: ЭКСПОПУЛ АО | J91: RUB*1000 | K91: NONE | L91: 111 | M91: 2022 | N91: SLSSFIX | O91: 325 | P91: false | R91: 324720,00000000000000 RUB*1000 > RUB*1000;
A92: BA090_08 | B92: 90.1010000 | C92: m15041200 | D92: Прокат латунный | E92: 654612 | F92: 12340 | G92: ООО "Сплав М" | H92: 72909 | I92: СПЛАВ М ООО | J92: RUB*1000 | K92: NONE | L92: 111 | M92: 2022 | N92: SLSSFIX | O92: 776 | P92: false | R92: 775981,59999999998000 RUB*1000 > RUB*1000;
A93: BA090_08 | B93: 90.1010000 | C93: m15041200 | D93: Прокат латунный | E93: 651986, 654256, 654265, 654363, 654462, 654463, 654469, 654473, 654480, 654485, 654488, 654499, 654500, 654506, 654507, 654508, 654513, 655771, 655865, 655947, 655948, 655950, 655953, 655954, 655955, 655961, 655962, 655967, 660212, 676009, 681305, 690869 | F93: 12363 | G93: ООО "ТЗК" | H93: 192342 | I93: ТЗК ООО | J93: RUB*1000 | K93: NONE | L93: 111 | M93: 2022 | N93: SLSSFIX | O93: 25796 | P93: false | R93: 254100,00000000000000 + 1784814,39999999990000 + 1807286,39999999990000 + 544140,40000000002000 + 163612,79999999999000 + 155001,00000000000000 + 1014367,20000000000000 + 1016400,00000000000000 + 165765,60000000001000 + 278249,40000000002000 + 264628,20000000001000 + 1503425,39999999990000 + 253918,00000000000000 + 158051,00000000000000 + 159214,39999999999000 + 406595,20000000001000 + 651743,59999999998000 + 328860,00000000000000 + 3137210,79999999980000 + 806981,00000000000000 + 1479212,39999999990000 + 2302779,20000000020000 + 558216,40000000002000 + 3740655,60000000010000 + 284688,00000000000000 + 539276,40000000002000 + 710191,80000000005000 + 106722,00000000000000 + 409589,40000000002000 + 155509,20000000001000 + 371852,79999999999000 + 283007,20000000001000 RUB*1000 > RUB*1000;
A94: BA090_08 | B94: 90.1010000 | C94: m15041200 | D94: Прокат латунный | E94: 654392 | F94: 12365 | G94: ОАО "Радиодеталь" | H94: 194918 | I94: РАДИОДЕТАЛЬ ОАО | J94: RUB*1000 | K94: NONE | L94: 111 | M94: 2022 | N94: SLSSFIX | O94: 540 | P94: false | R94: 539953,40000000002000 RUB*1000 > RUB*1000;
A95: BA090_08 | B95: 90.1010000 | C95: m15041200 | D95: Прокат латунный | E95: 653521, 656320, 656322, 657329, 657335, 657342, 657488, 657491, 657494, 657495, 658247, 658248, 702449 | F95: 12373 | G95: ООО "ТЕХПРОМРЕСУРС" | H95: 200905 | I95: ТЕХПРОМРЕСУРС ООО | J95: RUB*1000 | K95: NONE | L95: 111 | M95: 2022 | N95: SLSSFIX | O95: 3175 | P95: false | R95: 248547,20000000001000 + 100548,00000000000000 + 86259,60000000000600 + 225868,79999999999000 + 209260,79999999999000 + 233757,60000000001000 + 206769,60000000001000 + 210921,60000000001000 + 211752,00000000000000 + 205939,20000000001000 + 588984,00000000000000 + 494260,79999999999000 + 152364,79999999999000 RUB*1000 > RUB*1000;
A96: BA090_08 | B96: 90.1010000 | C96: m15041200 | D96: Прокат латунный | E96: 654388, 656262, 656263, 656264 | F96: 12378 | G96: ПК РОСТ ООО | H96: 208552 | I96: ПК РОСТ ООО | J96: RUB*1000 | K96: NONE | L96: 111 | M96: 2022 | N96: SLSSFIX | O96: 745 | P96: false | R96: 170139,60000000001000 + 170578,00000000000000 + 153061,20000000001000 + 251600,60000000001000 RUB*1000 > RUB*1000;
A97: BA090_08 | B97: 90.1010000 | C97: m15041200 | D97: Прокат латунный | E97: 651954, 651955, 654267, 654280, 654281, 654299, 654301, 654551, 654614, 655774, 655783, 657054, 657057, 657077, 705334, 708352, 708809, 708814 | F97: 12386 | G97: ТОРГОВО-ПРОИЗВОДСТВЕННОЕ УНИТАРНОЕ ПРЕДПРИЯТИЕ "КОЛОРПРОКАТ" | H97: 208941 | I97: КОЛОРПРОКАТ ТП УП | J97: RUB*1000 | K97: NONE | L97: 111 | M97: 2022 | N97: SLSSFIX | O97: 6212 | P97: false | R97: 144055,60000000001000 + 804665,59999999998000 + 132974,39999999999000 + 155563,00000000000000 + 1496814,39999999990000 + 126581,39999999999000 + 255293,79999999999000 + 532492,80000000005000 + 504951,90000000002000 + 174480,00000000000000 + 124317,00000000000000 + 145980,79999999999000 + 146941,20000000001000 + 145020,39999999999000 + 373400,90000000002000 + 364827,20000000001000 + 324764,40000000002000 + 259129,60000000001000 RUB*1000 > RUB*1000;
A98: BA090_08 | B98: 90.1010000 | C98: m15041200 | D98: Прокат латунный | E98: 651373, 654611, 654616, 654787, 654815, 654847, 654848, 654851, 656270, 657019, 657064, 657072, 670178, 688168, 688198, 688199, 702813 | F98: 12387 | G98: ОАО "МИНСКИЙ ЭЛЕКТРОТЕХНИЧЕСКИЙ ЗАВОД ИМЕНИ В.И. КОЗЛОВА" | H98: 208986 | I98: МЭТЗ ИМ. В.И.КОЗЛОВА ОАО | J98: RUB*1000 | K98: NONE | L98: 111 | M98: 2022 | N98: SLSSFIX | O98: 12782 | P98: false | R98: 2303829,60000000010000 + 516300,79999999999000 + 777980,59999999998000 + 209554,79999999999000 + 213796,79999999999000 + 216342,00000000000000 + 1274296,80000000000000 + 848400,00000000000000 + 1491487,20000000000000 + 248066,39999999999000 + 506216,79999999999000 + 770417,59999999998000 + 258150,39999999999000 + 1668802,80000000000000 + 415291,79999999999000 + 420806,40000000002000 + 642238,80000000005000 RUB*1000 > RUB*1000;
A99: BA090_08 | B99: 90.1010000 | C99: m15041200 | D99: Прокат латунный | E99: 657004, 657993, 658671, 696059 | F99: 12434 | G99: ООО "ЗАВОД СИСТЕМ ОХЛАЖДЕНИЯ" | H99: 208959 | I99: ЗАВОД СИСТЕМ ОХЛАЖДЕНИЯ ООО | J99: RUB*1000 | K99: NONE | L99: 111 | M99: 2022 | N99: SLSSFIX | O99: 28176 | P99: false | R99: 4140546,43999999990000 + 9716503,83000000010000 + 10207623,93999999900000 + 4111249,31999999980000 RUB*1000 > RUB*1000;
A100: BA090_08 | B100: 90.1010000 | C100: m15041200 | D100: Прокат латунный | E100: 654582, 654597, 654614, 655239, 655244, 657039, 657053, 657063, 657077, 657081, 658052, 706902 | F100: 12437 | G100: ОДО "СПЕЦМЕТПОСТАВКА" | H100: 209031 | I100: СПЕЦМЕТПОСТАВКА ОДО | J100: RUB*1000 | K100: NONE | L100: 111 | M100: 2022 | N100: SLSSFIX | O100: 3924 | P100: false | R100: 240600,00000000000000 + 143782,56000000000000 + 157813,10000000001000 + 653593,59999999998000 + 1351750,39999999990000 + 145322,39999999999000 + 147058,79999999999000 + 243487,20000000001000 + 470613,59999999998000 + 141472,79999999999000 + 154526,94000000000000 + 73659,60000000000600 RUB*1000 > RUB*1000;
A101: BA090_08 | B101: 90.1010000 | C101: m15041200 | D101: Прокат латунный | E101: 654595, 654601, 654607, 654612, 656074, 656076, 679277 | F101: 12763 | G101: ООО "ВИЛИНС" | H101: 194952 | I101: ВИЛИНС ООО | J101: RUB*1000 | K101: NONE | L101: 111 | M101: 2022 | N101: SLSSFIX | O101: 7682 | P101: false | R101: 163656,79999999999000 + 182576,35999999999000 + 4699247,20000000020000 + 1495480,80000000000000 + 270763,40000000002000 + 328356,00000000000000 + 542048,00000000000000 RUB*1000 > RUB*1000;
A102: BA090_08 | B102: 90.1010000 | C102: m15041200 | D102: Прокат латунный | E102: 652525, 658451, 651400, 652524, 653528, 654633, 654639, 656005, 653433, 654592, 654629, 654277, 659005, 693977, 700949, 653484, 651949, 651951, 652939, 652942, 652945, 655748, 655784, 684732, 694590, 656505, 655145, 657075, 657160, 656163, 657740, 709338, 655244, 657378, 657382, 708268, 658676, 656245, 700808, 658846, 656900, 684780, 655085, 657483, 657484, 657486, 657490, 657491, 657565, 657570, 657067, 657081, 688164, 654213, 654368, 654409, 654410, 654411, 654417, 654427, 654428, 655648, 655652, 655849, 654282, 701111, 655783, 658034, 657674, 654548, 654550, 656023, 651987, 658413, 655872, 702997, 656092, 654337, 655012, 657807, 651388, 651389, 651390, 654607, 658382, 658722, 658725, 654546, 654304, 655637, 655732, 655782, 655854, 656947, 657443, 658052, 683260, 656911, 657997, 654788 | F102: 2562 | G102: Покупатели проката ЦМ (внут.рынок) | H102: 1127 | I102: СЭГЗ АО | J102: RUB*1000 | K102: NONE | L102: 111 | M102: 2022 | N102: SLSSFIX | O102: 85658 | P102: false | R102: 78523,19999999999700 + 4453424,40000000040000 + 116246,46000000001000 + 135291,51999999999000 + 1177438,39999999990000 + 818259,04000000004000 + 470421,15000000002000 + 467202,59999999998000 + 190146,00000000000000 + 152350,79999999999000 + 157532,79999999999000 + 252664,39999999999000 + 1546858,39999999990000 + 545816,80000000005000 + 241201,20000000001000 + 2694722,24000000020000 + 233350,00000000000000 + 1688747,24000000000000 + 151581,50000000000000 + 975184,35999999999000 + 3011370,20000000020000 + 569912,50000000000000 + 134073,00000000000000 + 252288,00000000000000 + 383619,12000000000000 + 161644,06000000000000 + 3264696,39999999990000 + 152872,39999999999000 + 1404741,89999999990000 + 202113,60000000001000 + 889992,00000000000000 + 169161,60000000001000 + 2031622,39999999990000 + 402865,20000000001000 + 718109,59999999998000 + 2976414,04999999980000 + 165203,20000000001000 + 704428,19999999995000 + 10160038,72000000100000 + 1344703,91999999990000 + 617464,88000000000000 + 135831,79999999999000 + 206248,00000000000000 + 2513015,60000000010000 + 3955148,60000000010000 + 623467,59999999998000 + 3333762,00000000000000 + 1252762,00000000000000 + 423275,40000000002000 + 416200,00000000000000 + 2044167,34000000010000 + 154818,39999999999000 + 170069,76000000001000 + 252103,20000000001000 + 247150,00000000000000 + 503275,63000000000000 + 147395,76000000001000 + 161296,51999999999000 + 262345,04999999999000 + 1006636,22000000000000 + 150133,00000000000000 + 248902,00000000000000 + 256600,00000000000000 + 772966,43999999994000 + 496076,00000000000000 + 3345869,04000000000000 + 158297,60000000001000 + 615753,59999999998000 + 411937,20000000001000 + 246204,00000000000000 + 736267,19999999995000 + 352892,40000000002000 + 167328,00000000000000 + 99618,80000000000300 + 259178,39999999999000 + 257644,79999999999000 + 3198480,48000000000000 + 314938,79999999999000 + 365505,00000000000000 + 129445,20000000000000 + 329049,59999999998000 + 170944,00000000000000 + 122331,80000000000000 + 757190,00000000000000 + 361746,00000000000000 + 357478,44000000000000 + 767905,40000000002000 + 864058,80000000005000 + 150427,42000000001000 + 159008,85000000001000 + 467940,33000000002000 + 133264,56000000000000 + 156583,31000000000000 + 247874,72000000000000 + 825170,76000000001000 + 158846,82000000001000 + 151437,00000000000000 + 259854,10000000001000 + 1689942,80000000000000 + 869448,00000000000000 RUB*1000 > RUB*1000;
A103: BA090_08 | B103: 90.1010000 | C103: m15041200 | D103: Прокат латунный | E103: 653449, 653451, 653476, 653493, 653512, 653513, 654582, 654588, 654592, 654597, 654602, 654610, 654614, 655090, 655117, 655243, 655244, 655639, 655771, 656051, 656086, 656242, 656243, 656289, 656301, 656320, 657006, 657011, 657017, 657026, 657053, 657061, 657063, 657071, 657075, 657302, 657336, 657367, 657426, 657459, 657477, 657480, 657482, 657491, 657500, 657502, 657537, 657541, 657554, 657557, 657559, 657564, 657570, 657573, 657576, 658181, 658190, 658392, 658416, 658859, 679277, 681532 | F103: 2814 | G103: ООО "Промэко" | H103: 65765 | I103: ПРОМЭКО ООО | J103: RUB*1000 | K103: NONE | L103: 111 | M103: 2022 | N103: SLSSFIX | O103: 16818 | P103: false | R103: 135002,94000000000000 + 151936,48000000001000 + 224243,60000000001000 + 140439,29999999999000 + 130472,64000000000000 + 181212,00000000000000 + 900957,19999999995000 + 151060,39999999999000 + 434406,00000000000000 + 147815,94000000000000 + 243868,89999999999000 + 649268,40000000002000 + 308420,15000000002000 + 215107,20000000001000 + 327782,40000000002000 + 148544,00000000000000 + 433820,79999999999000 + 313746,21999999997000 + 151560,00000000000000 + 224089,60000000001000 + 151318,01999999999000 + 232428,29999999999000 + 261398,31000000000000 + 555751,76000000001000 + 128728,47000000000000 + 133077,60000000001000 + 302905,59999999998000 + 148463,60000000001000 + 152449,20000000001000 + 693690,00000000000000 + 149460,00000000000000 + 152449,20000000001000 + 601228,80000000005000 + 252089,20000000001000 + 149442,79999999999000 + 273177,09000000003000 + 135820,79999999999000 + 133233,60000000001000 + 590768,77000000002000 + 205131,00000000000000 + 127751,91000000000000 + 125226,72000000000000 + 127698,30000000000000 + 263257,59999999998000 + 129542,39999999999000 + 252358,39999999999000 + 125692,39999999999000 + 408637,20000000001000 + 124839,00000000000000 + 795430,18000000005000 + 124006,74000000001000 + 203075,64999999999000 + 119421,00000000000000 + 123799,77000000000000 + 1167891,20000000000000 + 366554,40000000002000 + 30159,75000000000000 + 131881,20000000001000 + 371040,00000000000000 + 128712,00000000000000 + 298820,35999999999000 + 255474,72000000000000 RUB*1000 > RUB*1000;
A104: BA090_08 | B104: 90.1010000 | C104: m15041200 | D104: Прокат латунный | E104: 654582, 654626, 654634, 655657, 655774, 657006, 657026, 657039, 657057, 657077, 658722, 659017 | F104: 2910 | G104: НАО ПКП "РОСТЕХКОМ" | H104: 19717 | I104: НАО ПКП РОСТЕХКОМ | J104: RUB*1000 | K104: NONE | L104: 111 | M104: 2022 | N104: SLSSFIX | O104: 2095 | P104: false | R104: 148860,00000000000000 + 150060,00000000000000 + 257352,89999999999000 + 155590,39999999999000 + 162288,00000000000000 + 145322,39999999999000 + 142435,20000000001000 + 149172,00000000000000 + 146284,79999999999000 + 151060,39999999999000 + 225789,12000000000000 + 260995,20000000001000 RUB*1000 > RUB*1000;
...

Sheet sap_11
A1: Код_sap | B1: Код_assoi | C1: Строка_АССОИ | D1: ТекстКлиент | E1: Группа материалов | F1: Материал | G1: ТекстГруппа материалов | H1: ТекстМатериал | I1: Код ОКВЭД | J1: Объем сбыта | K1: Выручка | L1: Себестоимость БУ | M1: РасходыНаПродажу | N1: Базисная ЕИ | O1: Формат_СС
E2: Сумма | O2: =SUM(O3:O2425) -> 2577873
A3: =VLOOKUP(D3,dict_name!L:M,2,FALSE) -> 214755 | B3: =VLOOKUP(A3,dict_name!B:D,3,FALSE) -> #N/A | C3: =VLOOKUP(E3,dict_prod!B:C,2,FALSE) -> m15041200 | D3: 13 ЭЛЕМЕНТ ООО | E3: 184500 | F3: 658722 | G3: Прокат латунный | H3: ЛИСТ ЛАТУНЬ 12*600*1500 ЛС59-1 ГПРХХ | J3: 0.706 | K3: 360162 | L3: 357478.44 | M3: 494.24 | N3: Т | O3: =ROUND(L3/1000,0) -> 357
A4: =VLOOKUP(D4,dict_name!L:M,2,FALSE) -> 214755 | B4: =VLOOKUP(A4,dict_name!B:D,3,FALSE) -> #N/A | C4: =VLOOKUP(E4,dict_prod!B:C,2,FALSE) -> m15041200 | D4: 13 ЭЛЕМЕНТ ООО | E4: 184500 | F4: 658725 | G4: Прокат латунный | H4: ЛИСТ ЛАТУНЬ 16*600*1500 ЛС59-1 ГПРХХ | J4: 1.517 | K4: 773670 | L4: 767905.4 | M4: 1061.68 | N4: Т | O4: =ROUND(L4/1000,0) -> 768
A5: =VLOOKUP(D5,dict_name!L:M,2,FALSE) -> 214755 | B5: =VLOOKUP(A5,dict_name!B:D,3,FALSE) -> #N/A | C5: =VLOOKUP(E5,dict_prod!B:C,2,FALSE) -> m15041300 | D5: 13 ЭЛЕМЕНТ ООО | E5: 188200 | F5: 657265 | G5: Прокат бронзовый | H5: ПРУТОК БРОНЗА 160 БРАЖ9-4 ПКРНХ | J5: 1.25 | K5: 718750 | L5: 714000 | M5: 986.32 | N5: Т | O5: =ROUND(L5/1000,0) -> 714
A6: =VLOOKUP(D6,dict_name!L:M,2,FALSE) -> 214755 | B6: =VLOOKUP(A6,dict_name!B:D,3,FALSE) -> #N/A | C6: =VLOOKUP(E6,dict_prod!B:C,2,FALSE) -> m15041300 | D6: 13 ЭЛЕМЕНТ ООО | E6: 188200 | F6: 658149 | G6: Прокат бронзовый | H6: ПРУТОК БРОНЗА 110 БРАМЦ9-2 ПКРНХ НД | J6: 0.962 | K6: 570466 | L6: 566810.4 | M6: 782.83 | N6: Т | O6: =ROUND(L6/1000,0) -> 567
A7: =VLOOKUP(D7,dict_name!L:M,2,FALSE) -> 212145 | B7: =VLOOKUP(A7,dict_name!B:D,3,FALSE) -> #N/A | C7: =VLOOKUP(E7,dict_prod!B:C,2,FALSE) -> m15041130 | D7: CGR TRANSILVANIA SRL | E7: 184400 | F7: 694324 | G7: Прокат медный | H7: ЛЕНТА МЕДЬ 1,2*39 CU-ETP Н065 EN 1652 | J7: 14.109 | K7: 10684346 | L7: 9618606.3 | M7: 20414.31 | N7: Т | O7: =ROUND(L7/1000,0) -> 9619
A8: =VLOOKUP(D8,dict_name!L:M,2,FALSE) -> 222292 | B8: =VLOOKUP(A8,dict_name!B:D,3,FALSE) -> #N/A | C8: =VLOOKUP(E8,dict_prod!B:C,2,FALSE) -> m15041130 | D8: MINMET TRADE DWC LLC | E8: 184400 | F8: 711150 | G8: Прокат медный | H8: ЛЕНТА МЕДЬ 1,8*151 CU-ETP R240 | J8: 6.692 | K8: 3675161.1 | L8: 3048094.5 | M8: 7022.03 | N8: Т | O8: =ROUND(L8/1000,0) -> 3048
A9: =VLOOKUP(D9,dict_name!L:M,2,FALSE) -> 222292 | B9: =VLOOKUP(A9,dict_name!B:D,3,FALSE) -> #N/A | C9: =VLOOKUP(E9,dict_prod!B:C,2,FALSE) -> m15041130 | D9: MINMET TRADE DWC LLC | E9: 184400 | F9: 711211 | G9: Прокат медный | H9: ЛЕНТА МЕДЬ 1,8*154 CU-ETP R240 | J9: 6.786 | K9: 3726784.7 | L9: 3090909.9 | M9: 7120.66 | N9: Т | O9: =ROUND(L9/1000,0) -> 3091
A10: =VLOOKUP(D10,dict_name!L:M,2,FALSE) -> 222292 | B10: =VLOOKUP(A10,dict_name!B:D,3,FALSE) -> #N/A | C10: =VLOOKUP(E10,dict_prod!B:C,2,FALSE) -> m15041130 | D10: MINMET TRADE DWC LLC | E10: 184400 | F10: 711212 | G10: Прокат медный | H10: ЛЕНТА МЕДЬ 1,8*157 CU-ETP R240 | J10: 6.8 | K10: 3734473.3 | L10: 3097286.7 | M10: 7135.36 | N10: Т | O10: =ROUND(L10/1000,0) -> 3097
A11: =VLOOKUP(D11,dict_name!L:M,2,FALSE) -> 68951 | B11: =VLOOKUP(A11,dict_name!B:D,3,FALSE) -> #N/A | C11: =VLOOKUP(E11,dict_prod!B:C,2,FALSE) -> m15098951 | D11: NOVA ЦИНК ТОО | E11: 252000 | F11: 694391 | G11: Шинная продукция | H11: ШИНА БЕЛШИНА 18.00R25 E4 BEL-183 | J11: 16 | K11: 1808000 | L11: 1808000 | M11: 3454.5 | N11: ШТ | O11: =ROUND(L11/1000,0) -> 1808
A12: =VLOOKUP(D12,dict_name!L:M,2,FALSE) -> 68951 | B12: =VLOOKUP(A12,dict_name!B:D,3,FALSE) -> #N/A | C12: =VLOOKUP(E12,dict_prod!B:C,2,FALSE) -> m15098951 | D12: NOVA ЦИНК ТОО | E12: 252000 | F12: 711824 | G12: Шинная продукция | H12: ШИНА БЕЛШИНА 24.00R35 E4 BEL-202 | J12: 12 | K12: 3576000 | L12: 3576000 | M12: 6832.5 | N12: ШТ | O12: =ROUND(L12/1000,0) -> 3576
A13: =VLOOKUP(D13,dict_name!L:M,2,FALSE) -> 11976 | B13: =VLOOKUP(A13,dict_name!B:D,3,FALSE) -> #N/A | C13: =VLOOKUP(E13,dict_prod!B:C,2,FALSE) -> m15041130 | D13: АВАР ПАО | E13: 184400 | F13: 707328 | G13: Прокат медный | H13: ЛЕНТА МЕДЬ 0,77*200 М1 ДПРПТ | J13: 3.156 | K13: 2032464 | L13: 1957351.2 | M13: 2789.09 | N13: Т | O13: =ROUND(L13/1000,0) -> 1957
A14: =VLOOKUP(D14,dict_name!L:M,2,FALSE) -> 11976 | B14: =VLOOKUP(A14,dict_name!B:D,3,FALSE) -> #N/A | C14: =VLOOKUP(E14,dict_prod!B:C,2,FALSE) -> m15041130 | D14: АВАР ПАО | E14: 184400 | F14: 711651 | G14: Прокат медный | H14: ЛЕНТА МЕДЬ 0,2*160 М1 ДПРПТ | J14: 1.029 | K14: 664760.69 | L14: 660852.39 | M14: 912.23 | N14: Т | O14: =ROUND(L14/1000,0) -> 661
A15: =VLOOKUP(D15,dict_name!L:M,2,FALSE) -> 11976 | B15: =VLOOKUP(A15,dict_name!B:D,3,FALSE) -> #N/A | C15: =VLOOKUP(E15,dict_prod!B:C,2,FALSE) -> m15041200 | D15: АВАР ПАО | E15: 184500 | F15: 701111 | G15: Прокат латунный | H15: ЛЕНТА ЛАТУНЬ 0,77*200 Л63 ДПРПП | J15: 7.012 | K15: 3512754.6 | L15: 3345869 | M15: 4820.45 | N15: Т | O15: =ROUND(L15/1000,0) -> 3346
A16: =VLOOKUP(D16,dict_name!L:M,2,FALSE) -> 11976 | B16: =VLOOKUP(A16,dict_name!B:D,3,FALSE) -> #N/A | C16: =VLOOKUP(E16,dict_prod!B:C,2,FALSE) -> m15041300 | D16: АВАР ПАО | E16: 188200 | F16: 710998 | G16: Прокат бронзовый | H16: ЛЕНТА БРОНЗА 0,15*200 БРОФ6,5-0,15 ДПРВТ | J16: 0.512 | K16: 665990 | L16: 664043.26 | M16: 913.92 | N16: Т | O16: =ROUND(L16/1000,0) -> 664
A17: =VLOOKUP(D17,dict_name!L:M,2,FALSE) -> 11976 | B17: =VLOOKUP(A17,dict_name!B:D,3,FALSE) -> #N/A | C17: =VLOOKUP(E17,dict_prod!B:C,2,FALSE) -> m15041300 | D17: АВАР ПАО | E17: 188200 | F17: 711213 | G17: Прокат бронзовый | H17: ЛЕНТА БРОНЗА 0,25*315 БРОФ6,5-0,15 ДПРПТ | J17: 0.479 | K17: 671020 | L17: 669198.66 | M17: 920.82 | N17: Т | O17: =ROUND(L17/1000,0) -> 669
A18: =VLOOKUP(D18,dict_name!L:M,2,FALSE) -> 196119 | B18: =VLOOKUP(A18,dict_name!B:D,3,FALSE) -> #N/A | C18: =VLOOKUP(E18,dict_prod!B:C,2,FALSE) -> m15041130 | D18: АВРОРА ЭЛЕКТРО ПК ООО | E18: 184400 | F18: 710349 | G18: Прокат медный | H18: ЛЕНТА МЕДЬ 0,5*500 М1 ДПРНМ | J18: 1.941 | K18: 1205361 | L18: 1197985.2 | M18: 1654.08 | N18: Т | O18: =ROUND(L18/1000,0) -> 1198
A19: =VLOOKUP(D19,dict_name!L:M,2,FALSE) -> 359 | B19: =VLOOKUP(A19,dict_name!B:D,3,FALSE) -> #N/A | C19: =VLOOKUP(E19,dict_prod!B:C,2,FALSE) -> m15041200 | D19: АВТОВАЗ АО | E19: 184500 | F19: 659358 | G19: Прокат латунный | H19: ТРУБА 67,8*53 ЛМЦАЖКС70-7-5-2-2-1 ПКР НД | J19: 5.098 | K19: 3216430.2 | L19: 3197057.8 | M19: 4413.82 | N19: Т | O19: =ROUND(L19/1000,0) -> 3197
... A2425: =VLOOKUP(D2425,dict_name!L:M,2,FALSE) -> 216712 | B2425: =VLOOKUP(A2425,dict_name!B:D,3,FALSE) -> #N/A | C2425: =VLOOKUP(E2425,dict_prod!B:C,2,FALSE) -> m15041300 | D2425: ЭТМ ООО | E2425: 188200 | F2425: 709689 | G2425: Прокат бронзовый | H2425: ПРУТОК БРОНЗА 175*700 БРАЖ9-4 ПКРНХ | J2425: 0.124 | K2425: 148998.4 | L2425: 148527.2 | M2425: 204.47 | N2425: Т | O2425: =ROUND(L2425/1000,0) -> 149

Sheet проверка_внешнего_ключа
A1: Код_sap | B1: ТекстКлиент | C1: sap | D1: assoi
C2: =SUM(C3:C263) -> 2577873 | D2: =SUM(D3:D263) -> 1841321
A3: 214755 | B3: 13 ЭЛЕМЕНТ ООО | C3: =SUMIFS(sap_11!O:O,sap_11!A:A,проверка_внешнего_ключа!A3) -> 2406 | D3: =SUMIFS(assoi!O:O,assoi!H:H,проверка_внешнего_ключа!A3) -> 0
A4: 212145 | B4: CGR TRANSILVANIA SRL | C4: =SUMIFS(sap_11!O:O,sap_11!A:A,проверка_внешнего_ключа!A4) -> 9619 | D4: =SUMIFS(assoi!O:O,assoi!H:H,проверка_внешнего_ключа!A4) -> 18478
A5: 222292 | B5: MINMET TRADE DWC LLC | C5: =SUMIFS(sap_11!O:O,sap_11!A:A,проверка_внешнего_ключа!A5) -> 9236 | D5: =SUMIFS(assoi!O:O,assoi!H:H,проверка_внешнего_ключа!A5) -> 0
A6: 68951 | B6: NOVA ЦИНК ТОО | C6: =SUMIFS(sap_11!O:O,sap_11!A:A,проверка_внешнего_ключа!A6) -> 5384 | D6: =SUMIFS(assoi!O:O,assoi!H:H,проверка_внешнего_ключа!A6) -> 1808
A7: 11976 | B7: АВАР ПАО | C7: =SUMIFS(sap_11!O:O,sap_11!A:A,проверка_внешнего_ключа!A7) -> 7297 | D7: =SUMIFS(assoi!O:O,assoi!H:H,проверка_внешнего_ключа!A7) -> 0
A8: 196119 | B8: АВРОРА ЭЛЕКТРО ПК ООО | C8: =SUMIFS(sap_11!O:O,sap_11!A:A,проверка_внешнего_ключа!A8) -> 1198 | D8: =SUMIFS(assoi!O:O,assoi!H:H,проверка_внешнего_ключа!A8) -> 0
A9: 359 | B9: АВТОВАЗ АО | C9: =SUMIFS(sap_11!O:O,sap_11!A:A,проверка_внешнего_ключа!A9) -> 17868 | D9: =SUMIFS(assoi!O:O,assoi!H:H,проверка_внешнего_ключа!A9) -> 17868
A10: 1790 | B10: АВТОДИЗЕЛЬ (ЯМЗ) ПАО | C10: =SUMIFS(sap_11!O:O,sap_11!A:A,проверка_внешнего_ключа!A10) -> 3129 | D10: =SUMIFS(assoi!O:O,assoi!H:H,проверка_внешнего_ключа!A10) -> 3129
A11: 74798 | B11: АВТОКОМПОНЕНТЫ - ГРУППА ГАЗ ООО | C11: =SUMIFS(sap_11!O:O,sap_11!A:A,проверка_внешнего_ключа!A11) -> 1233 | D11: =SUMIFS(assoi!O:O,assoi!H:H,проверка_внешнего_ключа!A11) -> 1233
A12: 219600 | B12: АВТОФОРМ ООО | C12: =SUMIFS(sap_11!O:O,sap_11!A:A,проверка_внешнего_ключа!A12) -> 167 | D12: =SUMIFS(assoi!O:O,assoi!H:H,проверка_внешнего_ключа!A12) -> 0
A13: 128692 | B13: АГРЕГАТ ПАО | C13: =SUMIFS(sap_11!O:O,sap_11!A:A,проверка_внешнего_ключа!A13) -> 2080 | D13: =SUMIFS(assoi!O:O,assoi!H:H,проверка_внешнего_ключа!A13) -> 0
A14: 178237 | B14: АДВЕРС ООО | C14: =SUMIFS(sap_11!O:O,sap_11!A:A,проверка_внешнего_ключа!A14) -> 1381 | D14: =SUMIFS(assoi!O:O,assoi!H:H,проверка_внешнего_ключа!A14) -> 0
... A263: 216712 | B263: ЭТМ ООО | C263: =SUMIFS(sap_11!O:O,sap_11!A:A,проверка_внешнего_ключа!A263) -> 467 | D263: =SUMIFS(assoi!O:O,assoi!H:H,проверка_внешнего_ключа!A263) -> 0

Sheet dict_name
A1: Контрагент КИС | B1: Код Контрагента КИС | C1: Контрагент АССОИ | D1: Код контрагента АССОИ | L1: ТекстКлиент | M1: Грузополучатель
L2: 13 ЭЛЕМЕНТ ООО | M2: 214755
A3: КУЗОЦМ АО | B3: 1258 | C3: ПАО "КУЗОЦМ" | D3: 2280 | L3: 13 ЭЛЕМЕНТ ООО | M3: 214755
A4: СТМ ООО | B4: 208535 | C4: СТМ ООО | D4: 12375 | L4: 13 ЭЛЕМЕНТ ООО | M4: 214755
A5: ЛИСТ СПБ ООО | B5: 69920 | C5: ООО "ЛИСТ СПб" | D5: 9950 | L5: 13 ЭЛЕМЕНТ ООО | M5: 214755
A6: НПЦ МЕТАЛЛУРГ ООО | B6: 66325 | C6: ООО "НПЦ Металлург" | D6: 10722 | L6: 13 ЭЛЕМЕНТ ООО | M6: 214755
A7: АЛЬМЕТ ООО | B7: 126128 | C7: ООО "АЛЬМЕТ" | D7: 10723 | L7: 13 ЭЛЕМЕНТ ООО | M7: 214755
A8: СВЕРДЛОВЭЛЕКТРО ООО | B8: 20784 | C8: ООО "СВЕРДЛОВЭЛЕКТРО" | D8: 10837 | L8: 13 ЭЛЕМЕНТ ООО | M8: 214755
A9: СПИРАЛЬ ООО | B9: 124818 | C9: ООО "СПИРАЛЬ" | D9: 10842 | L9: 13 ЭЛЕМЕНТ ООО | M9: 214755
A10: УРОМГАЗ-ИРБИТ ООО | B10: 125683 | C10: ООО "Уромгаз-Ирбит" | D10: 10845 | L10: 13 ЭЛЕМЕНТ ООО | M10: 214755
A11: ПОЗИС АО | B11: 135819 | C11: АО "ПОЗИС" | D11: 10848 | L11: 13 ЭЛЕМЕНТ ООО | M11: 214755
A12: ДКС АО | B12: 205357 | C12: АО "ДКС" | D12: 10856 | L12: 13 ЭЛЕМЕНТ ООО | M12: 214755
A13: НПК МЕТАПРОМ ООО | B13: 208503 | C13: НПК МЕТАПРОМ ООО | D13: 10857 | L13: 13 ЭЛЕМЕНТ ООО | M13: 214755
A14: МЕЛЬХИОР ООО | B14: 208504 | C14: МЕЛЬХИОР ООО | D14: 10858 | L14: 13 ЭЛЕМЕНТ ООО | M14: 214755
... A199: ШСУ ООО | B199: 80605 | C199: ООО "Шахтостроительное управление" | D199: 5325 | L199: MINMET TRADE DWC LLC | M199: 222292
L200: MINMET TRADE DWC LLC | M200: 222292
L201: MINMET TRADE DWC LLC | M201: 222292
L202: MINMET TRADE DWC LLC | M202: 222292
L203: MINMET TRADE DWC LLC | M203: 222292
L204: MINMET TRADE DWC LLC | M204: 222292
L205: MINMET TRADE DWC LLC | M205: 222292
L206: MINMET TRADE DWC LLC | M206: 222292
L207: MINMET TRADE DWC LLC | M207: 222292
L208: MINMET TRADE DWC LLC | M208: 222292
L209: MINMET TRADE DWC LLC | M209: 222292
L210: MINMET TRADE DWC LLC | M210: 222292
L211: MINMET TRADE DWC LLC | M211: 222292
... L37440: ЭТМ ООО | M37440: 216712

Sheet dict_prod
A1: Консолидирующая | P1: Консолидирующая (старая)
A2: Материал | B2: Группа материалов | C2: Код АССОИ | E2: Группа материалов | F2: Код АССОИ | G2: КА АССОИ (прочие) | I2: Наименование контрагента КИС | J2: Код контрагента АССОИ | P2: Материал | Q2: Группа материалов | R2: Код АССОИ
A3: 143048 | C3: m15041150 | E3: 184400 | F3: m15041130 | G3: 2562 | I3: СУМЗ ПАО | J3: 449 | P3: 143048 | R3: m15041150
A4: 641761 | C4: m15085100 | E4: 184200 | F4: m15041500 | G4: 2562 | I4: СВЯТОГОР АО | J4: 353 | P4: 641761 | R4: m15085100
A5: 641748 | C5: m15085100 | E5: 184500 | F5: m15041200 | G5: 2562 | I5: ШААЗ АО | J5: 362 | P5: 641748 | R5: m15085100
A6: 125269 | B6: 71000 | C6: =IFERROR(VLOOKUP(VALUE(B6),E:F,2,FALSE),"") | E6: 180000 | F6: m15041130 | G6: 2562 | I6: КЗОЦМ АО | J6: 468 | P6: 125269 | Q6: 71000 | R6: =IFERROR(VLOOKUP(VALUE(Q6),T:U,2,FALSE),"")
A7: 125269 | B7: 71240 | C7: =IFERROR(VLOOKUP(VALUE(B7),E:F,2,FALSE),"") | E7: 188200 | F7: m15041300 | G7: 2562 | I7: НАДЕЖДИНСКИЙ МЕТ.ЗАВОД ПАО | J7: 354 | P7: 125269 | Q7: 71240 | R7: =IFERROR(VLOOKUP(VALUE(Q7),T:U,2,FALSE),"")
A8: 562825 | B8: 71240 | C8: =IFERROR(VLOOKUP(VALUE(B8),E:F,2,FALSE),"") | E8: 173300 | F8: m15032100 | G8: 2562 | I8: ЧЦЗ АО | J8: 1108 | P8: 562825 | Q8: 71240 | R8: =IFERROR(VLOOKUP(VALUE(Q8),T:U,2,FALSE),"")
A9: 655582 | B9: 184400 | C9: =IFERROR(VLOOKUP(VALUE(B9),E:F,2,FALSE),"") -> m15041130 | E9: 351000 | F9: m150551231 | G9: 3582 | I9: ОРЕНБУРГСКИЙ РАДИАТОР ООО | J9: 471 | P9: 655582 | Q9: 184400 | R9: =IFERROR(VLOOKUP(VALUE(Q9),T:U,2,FALSE),"")
A10: 670758 | B10: 184500 | C10: =IFERROR(VLOOKUP(VALUE(B10),E:F,2,FALSE),"") -> m15041200 | E10: 350000 | F10: m15055024 | G10: 3582 | I10: МИХЕЛЬ ДАСТИН ООО | J10: 2809 | P10: 670758 | Q10: 184500 | R10: =IFERROR(VLOOKUP(VALUE(Q10),T:U,2,FALSE),"")
A11: 670760 | B11: 184500 | C11: =IFERROR(VLOOKUP(VALUE(B11),E:F,2,FALSE),"") -> m15041200 | E11: 141580 | F11: m15084752 | G11: 3582 | I11: УЧАЛИНСКИЙ ГОК АО | J11: 472 | P11: 670760 | Q11: 184500 | R11: =IFERROR(VLOOKUP(VALUE(Q11),T:U,2,FALSE),"")
A12: 670772 | B12: 184500 | C12: =IFERROR(VLOOKUP(VALUE(B12),E:F,2,FALSE),"") -> m15041200 | E12: 317632 | F12: =F11 -> m15084752 | G12: 3582 | I12: РЗ ОЦМ ПАО | J12: 415 | P12: 670772 | Q12: 184500 | R12: =IFERROR(VLOOKUP(VALUE(Q12),T:U,2,FALSE),"")
A13: 670796 | B13: 184500 | C13: =IFERROR(VLOOKUP(VALUE(B13),E:F,2,FALSE),"") -> m15041200 | E13: 314110 | F13: m15085520 | I13: УГМК-СТАЛЬ ООО | J13: 1047 | P13: 670796 | Q13: 184500 | R13: =IFERROR(VLOOKUP(VALUE(Q13),T:U,2,FALSE),"")
A14: 673677 | B14: 184400 | C14: =IFERROR(VLOOKUP(VALUE(B14),E:F,2,FALSE),"") -> m15041130 | E14: 460000 | F14: m150846029 | I14: БАШМЕДЬ ООО | J14: 1062 | P14: 673677 | Q14: 184400 | R14: =IFERROR(VLOOKUP(VALUE(Q14),T:U,2,FALSE),"")
A15: 673678 | B15: 184400 | C15: =IFERROR(VLOOKUP(VALUE(B15),E:F,2,FALSE),"") -> m15041130 | E15: 260000 | F15: m15081404 | I15: ГАЙСКИЙ ГОК ПАО | J15: 467 | P15: 673678 | Q15: 184400 | R15: =IFERROR(VLOOKUP(VALUE(Q15),T:U,2,FALSE),"")
A16: 673680 | B16: 184400 | C16: =IFERROR(VLOOKUP(VALUE(B16),E:F,2,FALSE),"") -> m15041130 | E16: 150000 | F16: m15063411 | I16: СИБКАБЕЛЬ АО | J16: 693 | P16: 673680 | Q16: 184400 | R16: =IFERROR(VLOOKUP(VALUE(Q16),T:U,2,FALSE),"")
A17: 650618 | B17: 184500 | C17: =IFERROR(VLOOKUP(VALUE(B17),E:F,2,FALSE),"") -> m15041200 | E17: 252000 | F17: m15098951 | I17: УРАЛЭЛЕКТРОМЕДЬ АО | J17: 352 | P17: 650618 | Q17: 184500 | R17: =IFERROR(VLOOKUP(VALUE(Q17),T:U,2,FALSE),"")
A18: 671362 | B18: 184400 | C18: =IFERROR(VLOOKUP(VALUE(B18),E:F,2,FALSE),"") -> m15041130 | E18: 40086 | F18: m150411201 | I18: СУХОЛОЖСКОЕ ЛИТЬЕ АО | J18: 857 | P18: 671362 | Q18: 184400 | R18: =IFERROR(VLOOKUP(VALUE(Q18),T:U,2,FALSE),"")
A19: 670798 | B19: 184400 | C19: =IFERROR(VLOOKUP(VALUE(B19),E:F,2,FALSE),"") -> m15041130 | E19: 143048 | F19: m15041150 | G19: 3295 | I19: УК КУЗБАССРАЗРЕЗУГОЛЬ АО | J19: 1067 | P19: 670798 | Q19: 184400 | R19: =IFERROR(VLOOKUP(VALUE(Q19),T:U,2,FALSE),"")
A20: 672847 | B20: 184400 | C20: =IFERROR(VLOOKUP(VALUE(B20),E:F,2,FALSE),"") -> m15041130 | E20: 641761 | F20: m15041150 | G20: 2371 | I20: АВТОДИЗЕЛЬ (ЯМЗ) ПАО | J20: 7223 | P20: 672847 | Q20: 184400 | R20: =IFERROR(VLOOKUP(VALUE(Q20),T:U,2,FALSE),"")
A21: 257514 | B21: 252000 | C21: =IFERROR(VLOOKUP(VALUE(B21),E:F,2,FALSE),"") -> m15098951 | E21: 641748 | F21: m15041150 | G21: 2371 | I21: ТЭМЗ АО | J21: 10875 | P21: 257514 | Q21: 252000 | R21: =IFERROR(VLOOKUP(VALUE(Q21),T:U,2,FALSE),"")
A22: 336035 | B22: 252000 | C22: =IFERROR(VLOOKUP(VALUE(B22),E:F,2,FALSE),"") -> m15098951 | E22: 173323 | F22: m15031600 | I22: КАЛУЖСКИЙ ТУРБИННЫЙ ЗАВОД ПАО | J22: 9814 | P22: 336035 | Q22: 252000 | R22: =IFERROR(VLOOKUP(VALUE(Q22),T:U,2,FALSE),"")
A23: 440585 | B23: 252000 | C23: =IFERROR(VLOOKUP(VALUE(B23),E:F,2,FALSE),"") -> m15098951 | I23: АЗ УРАЛ АО | J23: 3919 | P23: 440585 | Q23: 252000 | R23: =IFERROR(VLOOKUP(VALUE(Q23),T:U,2,FALSE),"")
A24: 518019 | B24: 252000 | C24: =IFERROR(VLOOKUP(VALUE(B24),E:F,2,FALSE),"") -> m15098951 | I24: СВЕРДЛ.ЗАВОД ТРАНСФОРМАТ.ТОКА | J24: 12395 | P24: 518019 | Q24: 252000 | R24: =IFERROR(VLOOKUP(VALUE(Q24),T:U,2,FALSE),"")
A25: 528261 | B25: 252000 | C25: =IFERROR(VLOOKUP(VALUE(B25),E:F,2,FALSE),"") -> m15098951 | P25: 528261 | Q25: 252000 | R25: =IFERROR(VLOOKUP(VALUE(Q25),T:U,2,FALSE),"")
A26: 591987 | B26: 252000 | C26: =IFERROR(VLOOKUP(VALUE(B26),E:F,2,FALSE),"") -> m15098951 | P26: 591987 | Q26: 252000 | R26: =IFERROR(VLOOKUP(VALUE(Q26),T:U,2,FALSE),"")
A27: 594714 | B27: 252000 | C27: =IFERROR(VLOOKUP(VALUE(B27),E:F,2,FALSE),"") -> m15098951 | P27: 594714 | Q27: 252000 | R27: =IFERROR(VLOOKUP(VALUE(Q27),T:U,2,FALSE),"")
A28: 657068 | B28: 184500 | C28: =IFERROR(VLOOKUP(VALUE(B28),E:F,2,FALSE),"") -> m15041200 | P28: 657068 | Q28: 184500 | R28: =IFERROR(VLOOKUP(VALUE(Q28),T:U,2,FALSE),"")
A29: 658172 | B29: 184500 | C29: =IFERROR(VLOOKUP(VALUE(B29),E:F,2,FALSE),"") -> m15041200 | P29: 658172 | Q29: 184500 | R29: =IFERROR(VLOOKUP(VALUE(Q29),T:U,2,FALSE),"")
A30: 659358 | B30: 184500 | C30: =IFERROR(VLOOKUP(VALUE(B30),E:F,2,FALSE),"") -> m15041200 | P30: 659358 | Q30: 184500 | R30: =IFERROR(VLOOKUP(VALUE(Q30),T:U,2,FALSE),"")
A31: 659897 | B31: 184500 | C31: =IFERROR(VLOOKUP(VALUE(B31),E:F,2,FALSE),"") -> m15041200 | P31: 659897 | Q31: 184500 | R31: =IFERROR(VLOOKUP(VALUE(Q31),T:U,2,FALSE),"")
A32: 660242 | B32: 184500 | C32: =IFERROR(VLOOKUP(VALUE(B32),E:F,2,FALSE),"") -> m15041200 | P32: 660242 | Q32: 184500 | R32: =IFERROR(VLOOKUP(VALUE(Q32),T:U,2,FALSE),"")
A33: 641695 | B33: 270000 | C33: =IFERROR(VLOOKUP(VALUE(B33),E:F,2,FALSE),"") | P33: 641695 | Q33: 270000 | R33: =IFERROR(VLOOKUP(VALUE(Q33),T:U,2,FALSE),"")
A34: 637563 | B34: 313000 | C34: =IFERROR(VLOOKUP(VALUE(B34),E:F,2,FALSE),"") | P34: 637563 | Q34: 313000 | R34: =IFERROR(VLOOKUP(VALUE(Q34),T:U,2,FALSE),"")
A35: 637661 | B35: 313000 | C35: =IFERROR(VLOOKUP(VALUE(B35),E:F,2,FALSE),"") | P35: 637661 | Q35: 313000 | R35: =IFERROR(VLOOKUP(VALUE(Q35),T:U,2,FALSE),"")
A36: 637678 | B36: 313000 | C36: =IFERROR(VLOOKUP(VALUE(B36),E:F,2,FALSE),"") | P36: 637678 | Q36: 313000 | R36: =IFERROR(VLOOKUP(VALUE(Q36),T:U,2,FALSE),"")
... A4808: 654273 | B4808: 184500 | C4808: =IFERROR(VLOOKUP(VALUE(B4808),E:F,2,FALSE),"") -> m15041200 | P4808: 654273 | Q4808: 184500 | R4808: =IFERROR(VLOOKUP(VALUE(Q4808),T:U,2,FALSE),"")
A4809: 697880 | B4809: 184400 | C4809: =IFERROR(VLOOKUP(VALUE(B4809),E:F,2,FALSE),"") -> m15041130 | R4809: =IFERROR(VLOOKUP(VALUE(Q4809),T:U,2,FALSE),"")
A4810: 697971 | B4810: 184400 | C4810: =IFERROR(VLOOKUP(VALUE(B4810),E:F,2,FALSE),"") -> m15041130 | R4810: =IFERROR(VLOOKUP(VALUE(Q4810),T:U,2,FALSE),"")
A4811: 697731 | B4811: 184400 | C4811: =IFERROR(VLOOKUP(VALUE(B4811),E:F,2,FALSE),"") -> m15041130 | R4811: =IFERROR(VLOOKUP(VALUE(Q4811),T:U,2,FALSE),"")
A4812: 697732 | B4812: 184400 | C4812: =IFERROR(VLOOKUP(VALUE(B4812),E:F,2,FALSE),"") -> m15041130 | R4812: =IFERROR(VLOOKUP(VALUE(Q4812),T:U,2,FALSE),"")
A4813: 655211 | B4813: 184500 | C4813: =IFERROR(VLOOKUP(VALUE(B4813),E:F,2,FALSE),"") -> m15041200 | R4813: =IFERROR(VLOOKUP(VALUE(Q4813),T:U,2,FALSE),"")
A4814: 691865 | B4814: 252000 | C4814: =IFERROR(VLOOKUP(VALUE(B4814),E:F,2,FALSE),"") -> m15098951 | R4814: =IFERROR(VLOOKUP(VALUE(Q4814),T:U,2,FALSE),"")
A4815: 693693 | B4815: 252000 | C4815: =IFERROR(VLOOKUP(VALUE(B4815),E:F,2,FALSE),"") -> m15098951 | R4815: =IFERROR(VLOOKUP(VALUE(Q4815),T:U,2,FALSE),"")
A4816: 693695 | B4816: 252000 | C4816: =IFERROR(VLOOKUP(VALUE(B4816),E:F,2,FALSE),"") -> m15098951 | R4816: =IFERROR(VLOOKUP(VALUE(Q4816),T:U,2,FALSE),"")
A4817: 693700 | B4817: 252000 | C4817: =IFERROR(VLOOKUP(VALUE(B4817),E:F,2,FALSE),"") -> m15098951 | R4817: =IFERROR(VLOOKUP(VALUE(Q4817),T:U,2,FALSE),"")
A4818: 603215 | B4818: 393000 | C4818: =IFERROR(VLOOKUP(VALUE(B4818),E:F,2,FALSE),"") | R4818: =IFERROR(VLOOKUP(VALUE(Q4818),T:U,2,FALSE),"")
A4819: 160411 | B4819: 545690 | C4819: =IFERROR(VLOOKUP(VALUE(B4819),E:F,2,FALSE),"") | R4819: =IFERROR(VLOOKUP(VALUE(Q4819),T:U,2,FALSE),"")
A4820: 293842 | B4820: 545690 | C4820: =IFERROR(VLOOKUP(VALUE(B4820),E:F,2,FALSE),"") | R4820: =IFERROR(VLOOKUP(VALUE(Q4820),T:U,2,FALSE),"")
... A5945: 694322 | B5945: 184400 | C5945: =IFERROR(VLOOKUP(VALUE(B5945),E:F,2,FALSE),"") -> m15041130 | R5945: =IFERROR(VLOOKUP(VALUE(Q5945),T:U,2,FALSE),"")
A5946: 651190 | B5946: 184400 | C5946: =IFERROR(VLOOKUP(VALUE(B5946),E:F,2,FALSE),"") -> m15041130
A5947: 688491 | B5947: 188200 | C5947: =IFERROR(VLOOKUP(VALUE(B5947),E:F,2,FALSE),"") -> m15041300
A5948: 650731 | B5948: 184400 | C5948: =IFERROR(VLOOKUP(VALUE(B5948),E:F,2,FALSE),"") -> m15041130
A5949: 689657 | B5949: 184400 | C5949: =IFERROR(VLOOKUP(VALUE(B5949),E:F,2,FALSE),"") -> m15041130
A5950: 695129 | B5950: 184400 | C5950: =IFERROR(VLOOKUP(VALUE(B5950),E:F,2,FALSE),"") -> m15041130
A5951: 695220 | B5951: 184400 | C5951: =IFERROR(VLOOKUP(VALUE(B5951),E:F,2,FALSE),"") -> m15041130
A5952: 695231 | B5952: 184400 | C5952: =IFERROR(VLOOKUP(VALUE(B5952),E:F,2,FALSE),"") -> m15041130
A5953: 695237 | B5953: 184400 | C5953: =IFERROR(VLOOKUP(VALUE(B5953),E:F,2,FALSE),"") -> m15041130
A5954: 695238 | B5954: 184400 | C5954: =IFERROR(VLOOKUP(VALUE(B5954),E:F,2,FALSE),"") -> m15041130
A5955: 695239 | B5955: 184400 | C5955: =IFERROR(VLOOKUP(VALUE(B5955),E:F,2,FALSE),"") -> m15041130
A5956: 658387 | B5956: 184500 | C5956: =IFERROR(VLOOKUP(VALUE(B5956),E:F,2,FALSE),"") -> m15041200
A5957: 698588 | B5957: 184500 | C5957: =IFERROR(VLOOKUP(VALUE(B5957),E:F,2,FALSE),"") -> m15041200
... A6472: 656267 | B6472: 184500 | C6472: =IFERROR(VLOOKUP(VALUE(B6472),E:F,2,FALSE),"") -> m15041200
A6473: 658722 | B6473: 184500 | C6473: =IFERROR(VLOOKUP(VALUE(B6473),E:F,2,FALSE),"") -> m15041200
A6474: 658725 | B6474: 184500 | C6474: =IFERROR(VLOOKUP(VALUE(B6474),E:F,2,FALSE),"") -> m15041200
A6475: 657265 | B6475: 188200 | C6475: =IFERROR(VLOOKUP(VALUE(B6475),E:F,2,FALSE),"") -> m15041300
A6476: 658149 | B6476: 188200 | C6476: =IFERROR(VLOOKUP(VALUE(B6476),E:F,2,FALSE),"") -> m15041300
A6477: 694324 | B6477: 184400 | C6477: =IFERROR(VLOOKUP(VALUE(B6477),E:F,2,FALSE),"") -> m15041130
A6478: 711150 | B6478: 184400 | C6478: =IFERROR(VLOOKUP(VALUE(B6478),E:F,2,FALSE),"") -> m15041130
A6479: 711211 | B6479: 184400 | C6479: =IFERROR(VLOOKUP(VALUE(B6479),E:F,2,FALSE),"") -> m15041130
A6480: 711212 | B6480: 184400 | C6480: =IFERROR(VLOOKUP(VALUE(B6480),E:F,2,FALSE),"") -> m15041130
A6481: 694391 | B6481: 252000 | C6481: =IFERROR(VLOOKUP(VALUE(B6481),E:F,2,FALSE),"") -> m15098951
A6482: 711824 | B6482: 252000 | C6482: =IFERROR(VLOOKUP(VALUE(B6482),E:F,2,FALSE),"") -> m15098951
A6483: 707328 | B6483: 184400 | C6483: =IFERROR(VLOOKUP(VALUE(B6483),E:F,2,FALSE),"") -> m15041130
A6484: 711651 | B6484: 184400 | C6484: =IFERROR(VLOOKUP(VALUE(B6484),E:F,2,FALSE),"") -> m15041130
A6485: 701111 | B6485: 184500 | C6485: =IFERROR(VLOOKUP(VALUE(B6485),E:F,2,FALSE),"") -> m15041200
A6486: 710998 | B6486: 188200 | C6486: =IFERROR(VLOOKUP(VALUE(B6486),E:F,2,FALSE),"") -> m15041300
A6487: 711213 | B6487: 188200 | C6487: =IFERROR(VLOOKUP(VALUE(B6487),E:F,2,FALSE),"") -> m15041300
A6488: 710349 | B6488: 184400 | C6488: =IFERROR(VLOOKUP(VALUE(B6488),E:F,2,FALSE),"") -> m15041130
A6489: 659358 | B6489: 184500 | C6489: =IFERROR(VLOOKUP(VALUE(B6489),E:F,2,FALSE),"") -> m15041200
... A8895: 709689 | B8895: 188200 | C8895: =IFERROR(VLOOKUP(VALUE(B8895),E:F,2,FALSE),"") -> m15041300
